Workbook

Sheet 对话配置表
A1: convert(ResTask.proto, table_DialogueConf, DialogueConf.pbin)
A2: 对话id | B2: 策划备注 | C2: 对话序列 | D2: 策划备注 | E2: 版本 | F2: 角色名称 | G2: 角色名称（key） | H2: 图集路径 | I2: 图片 | J2: 文本内容 | K2: 文本内容(源文本) | L2: 【海外对话表演】模型路径配置 | M2: 【海外对话表演】模型动画名称 | N2: 【海外对话表演】模型结束动画名称 | O2: 海外对话表演】模型位置 | P2: 海外对话表演】结束模型位置 | Q2: 海外对话表演】模型运动时间 | R2: 【海外对话表演】镜头位置参数 | S2: 【海外对话表演】结束镜头位置参数 | T2: 不要翻译 | U2: 对话框样式 | V2: 对话框左右 | W2: 触发结点 | X2: 关卡 | Y2: 是否使用3D播放 | Z2: 语音和背景音 | AA2: 跳过对话终止语音（配了否依然会被其他语音卡掉） | AB2: 语音和背景结束音 | AC2: 口型配置 | AD2: 语音时长工具生成 | AE2: 自动关闭时间 | AF2: 多语言偏移生成 | AG2: 多语言偏移 | AH2: 允许跳过的最短时间 | AI2: 【海外】对话每页字显示完后停留时长 | AJ2: S3跳过时间(不配置无法跳过) | AK2: 跳过后提示文本 | AL2: 播放速度(每秒多少字） | AM2: 角色模型 | AN2: 表演动作 | AO2: 蓝图objID | AP2: 对话弹窗颜色 | AQ2: 气泡偏移 | AR2: 隐藏背景模糊 | AS2: 【海外对话表演】模型对话时音乐 | AT2: 标签后文本 | AU2: 初始对话文本 | AV2: 对话ID关联 | AW2: 标签文本1 | AX2: 标签文本2 | AY2: 标签文本3 | AZ2: 标签文本4 | BA2: 副本部队ID | BB2: 副本部队ID中的SoldiderID | BC2: 绑定副本部队ID中的Soldider尺寸要大于的值 | BD2: 迷雾战场中气泡对象,-1代表玩家部队，其他代表蓝图objID | BE2: 迷雾战场气泡偏移 | BF2: 【海外】背景对话样式(0蓝色,1红色) | BG2: timeline名 | BH2: 跳到的timeline时间（秒数） | BI2: 对应语音是否需要转换多语言事件
A3: dialogueID | C3: contextSequence | G3: name | H3: altasPath | I3: picture | J3: textList | L3: modelPathID | M3: modelAnimNameAndCount[|] | N3: modelEndAnimName | O3: modelPos[|] | P3: modelEndPos[|] | Q3: modelRunTime | R3: cameraParam[|] | S3: cameraEndParam[|] | T3: DNT | U3: dialogueType | V3: dialoguePos | W3: groupId | X3: raidId | Y3: isIn3D | Z3: voiceList[|] | AA3: stopVoiceWhenSkip | AB3: endVoiceList[|] | AC3: lipSyncData | AD3: endTimeGenerate | AE3: endTime | AF3: endTimeOffsetGenerate | AG3: endTimeOffset | AH3: skipDelay | AI3: cutPageShowTime | AJ3: skipTime | AK3: skipTipsContent | AL3: textSpeed | AM3: npcId | AN3: animationName | AO3: BPobjID | AP3: dialogueColor | AQ3: bubbleOffset[;] | AR3: hideBlur | AS3: overseaSetSwtich | BA3: bubbleBindObjId | BB3: bubbleBindSoldierId | BC3: bubbleBindSoldierScale | BD3: fogwarBubbleBindObj | BE3: fogwarBubbleBindOffset[|] | BF3: bgStyle | BG3: timeline.id | BH3: timeline.time | BI3: isVoiceNeedMultiLang
A4: 1 | C4: 1 | E4: DEMO | F4: =VLOOKUP(G4,'#TID_base_up'!B:C,2,0) -> 随从 | G4: TID_DialogueConf_1001_name_CN_Main | H4: icon_guidechara.smash | I4: frame_s_xsdh_002 | J4: TID_DialogueConf_1_textList_CN_Main | T4: 1 | U4: 1 | V4: 0 | W4: 1 | X4: 0 | AD4: 5.5 | AE4: 6.5 | AG4: tr_TR|0;zh_TW|0 | AH4: 0.1 | AL4: 10 | AM4: assets/bundleresources/characters/a/hero/p_ah_joa.prefab | AN4: DJ | AT4: =IF($AU4="","",SUBSTITUTE(SUBSTITUTE(SUBSTITUTE(SUBSTITUTE($AU4,IF($AW4="","",$AW4),IF($AW4="","",CONCATENATE("<color=#FFCC71>",$AW4,"</color>"))),IF($AX4="","",$AX4),IF($AX4="","",CONCATENATE("<color=#FFCC71>",$AX4,"</color>"))),IF($AY4="","",$AY4),IF($AY4="","",CONCATENATE("<color=#FFCC71>",$AY4,"</color>"))),IF($AZ4="","",$AZ4),IF($AZ4="","",CONCATENATE("<color=#FFCC71>",$AZ4,"</color>")))) -> 领主，关押村民们的营地就在前方。 | AU4: 领主，关押村民们的营地就在前方。
A5: 2 | C5: 1 | E5: DEMO | F5: =VLOOKUP(G5,'#TID_base_up'!B:C,2,0) -> 我 | G5: TID_DialogueConf_2_name_23996658795_CN_Main | H5: icon_guidechara.smash | I5: frame_s_xsdh_002 | J5: TID_DialogueConf_2_textList_CN_Main | T5: 1 | U5: 1 | V5: 0 | W5: 1 | X5: 0 | AD5: 5.5 | AE5: 6.5 | AH5: 0.1 | AL5: 10 | AM5: assets/bundleresources/characters/a/hero/p_ah_joa.prefab | AN5: talk_normal | AT5: =IF($AU5="","",SUBSTITUTE(SUBSTITUTE(SUBSTITUTE(SUBSTITUTE($AU5,IF($AW5="","",$AW5),IF($AW5="","",CONCATENATE("<color=#FFCC71>",$AW5,"</color>"))),IF($AX5="","",$AX5),IF($AX5="","",CONCATENATE("<color=#FFCC71>",$AX5,"</color>"))),IF($AY5="","",$AY5),IF($AY5="","",CONCATENATE("<color=#FFCC71>",$AY5,"</color>"))),IF($AZ5="","",$AZ5),IF($AZ5="","",CONCATENATE("<color=#FFCC71>",$AZ5,"</color>")))) -> 必须拯救他们。这是我跟姐姐的约定？ | AU5: 必须拯救他们。这是我跟姐姐的约定？
A6: 2 | C6: 2 | E6: DEMO | F6: =VLOOKUP(G6,'#TID_base_up'!B:C,2,0) -> 我 | G6: TID_DialogueConf_2_name_23996658795_CN_Main | H6: icon_guidechara.smash | I6: frame_s_xsdh_002 | J6: TID_DialogueConf_2_textList_705307478613_CN_Main | T6: 1 | U6: 1 | V6: 0 | W6: 1 | X6: 0 | AD6: 5.5 | AE6: 6.5 | AH6: 0.1 | AL6: 10 | AM6: assets/bundleresources/characters/a/hero/p_ah_joa.prefab | AN6: talk_normal | AT6: =IF($AU6="","",SUBSTITUTE(SUBSTITUTE(SUBSTITUTE(SUBSTITUTE($AU6,IF($AW6="","",$AW6),IF($AW6="","",CONCATENATE("<color=#FFCC71>",$AW6,"</color>"))),IF($AX6="","",$AX6),IF($AX6="","",CONCATENATE("<color=#FFCC71>",$AX6,"</color>"))),IF($AY6="","",$AY6),IF($AY6="","",CONCATENATE("<color=#FFCC71>",$AY6,"</color>"))),IF($AZ6="","",$AZ6),IF($AZ6="","",CONCATENATE("<color=#FFCC71>",$AZ6,"</color>")))) -> 出发！消灭守军。 | AU6: 出发！消灭守军。
A7: 3 | C7: 1 | E7: DEMO | F7: =VLOOKUP(G7,'#TID_base_up'!B:C,2,0) -> 村民甲 | G7: TID_DialogueConf_3_name_CN_Main | H7: icon_guidechara.smash | I7: frame_s_xsdh_002 | J7: TID_DialogueConf_3_textList_CN_Main | T7: 1 | U7: 1 | V7: 0 | W7: 1 | X7: 0 | AD7: 5.5 | AE7: 6.5 | AH7: 0.1 | AL7: 10 | AM7: assets/bundleresources/characters/a/hero/p_ah_joa.prefab | AN7: tv_idle | AT7: =IF($AU7="","",SUBSTITUTE(SUBSTITUTE(SUBSTITUTE(SUBSTITUTE($AU7,IF($AW7="","",$AW7),IF($AW7="","",CONCATENATE("<color=#FFCC71>",$AW7,"</color>"))),IF($AX7="","",$AX7),IF($AX7="","",CONCATENATE("<color=#FFCC71>",$AX7,"</color>"))),IF($AY7="","",$AY7),IF($AY7="","",CONCATENATE("<color=#FFCC71>",$AY7,"</color>"))),IF($AZ7="","",$AZ7),IF($AZ7="","",CONCATENATE("<color=#FFCC71>",$AZ7,"</color>")))) -> 天啊！敌人的将军来了，就在前方。 | AU7: 天啊！敌人的将军来了，就在前方。
A8: 4 | C8: 1 | E8: DEMO | F8: =VLOOKUP(G8,'#TID_base_up'!B:C,2,0) -> 魏兰 | G8: TID_DialogueConf_4_name_CN_Main | H8: icon_guidechara.smash | I8: frame_s_xsdh_002 | J8: TID_DialogueConf_4_textList_CN_Main | T8: 1 | U8: 1 | V8: 0 | W8: 1 | X8: 0 | AD8: 5.5 | AE8: 6.5 | AH8: 0.1 | AL8: 10 | AM8: assets/bundleresources/characters/a/hero/p_ah_joa.prefab | AN8: talk_normal | AT8: =IF($AU8="","",SUBSTITUTE(SUBSTITUTE(SUBSTITUTE(SUBSTITUTE($AU8,IF($AW8="","",$AW8),IF($AW8="","",CONCATENATE("<color=#FFCC71>",$AW8,"</color>"))),IF($AX8="","",$AX8),IF($AX8="","",CONCATENATE("<color=#FFCC71>",$AX8,"</color>"))),IF($AY8="","",$AY8),IF($AY8="","",CONCATENATE("<color=#FFCC71>",$AY8,"</color>"))),IF($AZ8="","",$AZ8),IF($AZ8="","",CONCATENATE("<color=#FFCC71>",$AZ8,"</color>")))) -> 我是花木兰。前来营救！ | AU8: 我是花木兰。前来营救！
A9: 5 | C9: 1 | E9: DEMO | F9: =VLOOKUP(G9,'#TID_base_up'!B:C,2,0) -> 随从 | G9: TID_DialogueConf_1001_name_CN_Main | H9: icon_campaign_npc.smash | I9: npc_campaign_half011 | J9: TID_DialogueConf_5_textList_CN_Main | T9: 1 | U9: 2 | V9: 0 | W9: 1 | X9: 0 | AD9: 5.5 | AE9: 6.5 | AH9: 0.1 | AL9: 10 | AT9: =IF($AU9="","",SUBSTITUTE(SUBSTITUTE(SUBSTITUTE(SUBSTITUTE($AU9,IF($AW9="","",$AW9),IF($AW9="","",CONCATENATE("<color=#FFCC71>",$AW9,"</color>"))),IF($AX9="","",$AX9),IF($AX9="","",CONCATENATE("<color=#FFCC71>",$AX9,"</color>"))),IF($AY9="","",$AY9),IF($AY9="","",CONCATENATE("<color=#FFCC71>",$AY9,"</color>"))),IF($AZ9="","",$AZ9),IF($AZ9="","",CONCATENATE("<color=#FFCC71>",$AZ9,"</color>")))) -> 这是小对话测试1 | AU9: 这是小对话测试1
A10: 5 | C10: 2 | E10: DEMO | F10: =VLOOKUP(G10,'#TID_base_up'!B:C,2,0) -> 随从 | G10: TID_DialogueConf_1001_name_CN_Main | H10: icon_guidechara.smash | I10: frame_s_xsdh_002 | J10: TID_DialogueConf_5_textList_960981524853_CN_Main | T10: 1 | U10: 2 | V10: 0 | W10: 1 | X10: 0 | AD10: 5.5 | AE10: 6.5 | AH10: 0.1 | AL10: 10 | AT10: =IF($AU10="","",SUBSTITUTE(SUBSTITUTE(SUBSTITUTE(SUBSTITUTE($AU10,IF($AW10="","",$AW10),IF($AW10="","",CONCATENATE("<color=#FFCC71>",$AW10,"</color>"))),IF($AX10="","",$AX10),IF($AX10="","",CONCATENATE("<color=#FFCC71>",$AX10,"</color>"))),IF($AY10="","",$AY10),IF($AY10="","",CONCATENATE("<color=#FFCC71>",$AY10,"</color>"))),IF($AZ10="","",$AZ10),IF($AZ10="","",CONCATENATE("<color=#FFCC71>",$AZ10,"</color>")))) -> 这是小对话测试2 | AU10: 这是小对话测试2
A11: 1001 | C11: 1 | E11: DEMO | F11: =VLOOKUP(G11,'#TID_base_up'!B:C,2,0) -> 随从 | G11: TID_DialogueConf_1001_name_CN_Main | J11: TID_DialogueConf_1001_textList_CN_Main | T11: 1 | U11: 3 | V11: 0 | W11: 1 | X11: 0 | AD11: 5.5 | AE11: 6.5 | AH11: 0.1 | AL11: 10 | AT11: =IF($AU11="","",SUBSTITUTE(SUBSTITUTE(SUBSTITUTE(SUBSTITUTE($AU11,IF($AW11="","",$AW11),IF($AW11="","",CONCATENATE("<color=#FFCC71>",$AW11,"</color>"))),IF($AX11="","",$AX11),IF($AX11="","",CONCATENATE("<color=#FFCC71>",$AX11,"</color>"))),IF($AY11="","",$AY11),IF($AY11="","",CONCATENATE("<color=#FFCC71>",$AY11,"</color>"))),IF($AZ11="","",$AZ11),IF($AZ11="","",CONCATENATE("<color=#FFCC71>",$AZ11,"</color>")))) -> 我是一个小气泡文本 | AU11: 我是一个小气泡文本
A12: 1002 | C12: 1 | E12: DEMO | F12: =VLOOKUP(G12,'#TID_base_up'!B:C,2,0) -> 随从 | G12: TID_DialogueConf_1001_name_CN_Main | J12: TID_DialogueConf_1002_textList_CN_Main | T12: 1 | U12: 3 | V12: 0 | W12: 1 | X12: 0 | AD12: 5.5 | AE12: 6.5 | AH12: 0.1 | AL12: 10 | AT12: =IF($AU12="","",SUBSTITUTE(SUBSTITUTE(SUBSTITUTE(SUBSTITUTE($AU12,IF($AW12="","",$AW12),IF($AW12="","",CONCATENATE("<color=#FFCC71>",$AW12,"</color>"))),IF($AX12="","",$AX12),IF($AX12="","",CONCATENATE("<color=#FFCC71>",$AX12,"</color>"))),IF($AY12="","",$AY12),IF($AY12="","",CONCATENATE("<color=#FFCC71>",$AY12,"</color>"))),IF($AZ12="","",$AZ12),IF($AZ12="","",CONCATENATE("<color=#FFCC71>",$AZ12,"</color>")))) -> 我是一个小气泡文本，但是我特别的长，用来测试气泡文本的自动缩放功能。哈哈哈哈哈哈哈哈。 | AU12: 我是一个小气泡文本，但是我特别的长，用来测试气泡文本的自动缩放功能。哈哈哈哈哈哈哈哈。
A13: 1002 | C13: 2 | E13: DEMO | F13: =VLOOKUP(G13,'#TID_base_up'!B:C,2,0) -> 随从 | G13: TID_DialogueConf_1001_name_CN_Main | J13: TID_DialogueConf_1002_textList_507990760778_CN_Main | T13: 1 | U13: 3 | V13: 0 | W13: 1 | X13: 0 | AD13: 5.5 | AE13: 6.5 | AH13: 0.1 | AL13: 10 | AT13: =IF($AU13="","",SUBSTITUTE(SUBSTITUTE(SUBSTITUTE(SUBSTITUTE($AU13,IF($AW13="","",$AW13),IF($AW13="","",CONCATENATE("<color=#FFCC71>",$AW13,"</color>"))),IF($AX13="","",$AX13),IF($AX13="","",CONCATENATE("<color=#FFCC71>",$AX13,"</color>"))),IF($AY13="","",$AY13),IF($AY13="","",CONCATENATE("<color=#FFCC71>",$AY13,"</color>"))),IF($AZ13="","",$AZ13),IF($AZ13="","",CONCATENATE("<color=#FFCC71>",$AZ13,"</color>")))) -> 这是小气泡文本的第二段，过了五秒钟我会出现。这是小气泡文本的第二段，过了五秒钟我会出现。这是小气泡文本的第二段，过了五秒钟我会出现。 | AU13: 这是小气泡文本的第二段，过了五秒钟我会出现。这是小气泡文本的第二段，过了五秒钟我会出现。这是小气泡文本的第二段，过了五秒钟我会出现。
A14: 10001 | C14: 1 | E14: DEMO | F14: =VLOOKUP(G14,'#TID_base_up'!B:C,2,0) -> 琼恩 | G14: TID_DialogueConf_10001_name_CN_Main | H14: icon_campaign_npc.smash | I14: npc_campaign_half006 | J14: TID_DialogueConf_10001_textList_CN_Main | T14: 1 | U14: 2 | V14: 0 | X14: 1005 | AD14: 4 | AE14: 5 | AH14: 0.1 | AL14: 10 | AT14: =IF($AU14="","",SUBSTITUTE(SUBSTITUTE(SUBSTITUTE(SUBSTITUTE($AU14,IF($AW14="","",$AW14),IF($AW14="","",CONCATENATE("<color=#FFCC71>",$AW14,"</color>"))),IF($AX14="","",$AX14),IF($AX14="","",CONCATENATE("<color=#FFCC71>",$AX14,"</color>"))),IF($AY14="","",$AY14),IF($AY14="","",CONCATENATE("<color=#FFCC71>",$AY14,"</color>"))),IF($AZ14="","",$AZ14),IF($AZ14="","",CONCATENATE("<color=#FFCC71>",$AZ14,"</color>")))) -> 说好了在这里汇合，怎么到现在都不见人影？ | AU14: 说好了在这里汇合，怎么到现在都不见人影？
A15: 10002 | C15: =IF(A15=A14,C14+1,1) -> 1 | E15: DEMO | F15: =VLOOKUP(G15,'#TID_base_up'!B:C,2,0) -> 强盗 | G15: TID_DialogueConf_10002_name_CN_Main | H15: icon_guidechara.smash | I15: =VLOOKUP(F15,'#Sheet1'!$J$2:$L$10,2,FALSE) -> frame_s_xsdh_005 | J15: TID_DialogueConf_10002_textList_CN_Main | T15: 1 | U15: 2 | V15: 0 | X15: 1005 | AD15: 3.7 | AE15: 4.7 | AH15: 0.1 | AL15: 10 | AT15: =IF($AU15="","",SUBSTITUTE(SUBSTITUTE(SUBSTITUTE(SUBSTITUTE($AU15,IF($AW15="","",$AW15),IF($AW15="","",CONCATENATE("<color=#FFCC71>",$AW15,"</color>"))),IF($AX15="","",$AX15),IF($AX15="","",CONCATENATE("<color=#FFCC71>",$AX15,"</color>"))),IF($AY15="","",$AY15),IF($AY15="","",CONCATENATE("<color=#FFCC71>",$AY15,"</color>"))),IF($AZ15="","",$AZ15),IF($AZ15="","",CONCATENATE("<color=#FFCC71>",$AZ15,"</color>")))) -> 喂！女人！快把值钱的东西全部交出来！ | AU15: 喂！女人！快把值钱的东西全部交出来！
A16: 10002 | C16: =IF(A16=A15,C15+1,1) -> 2 | E16: DEMO | F16: =VLOOKUP(G16,'#TID_base_up'!B:C,2,0) -> 琼恩 | G16: TID_DialogueConf_10001_name_CN_Main | H16: icon_campaign_npc.smash | I16: npc_campaign_half006 | J16: TID_DialogueConf_10002_textList_286297514590_CN_Main | T16: 1 | U16: 2 | V16: 0 | X16: 1005 | AD16: 5.2 | AE16: 6.2 | AH16: 0.1 | AL16: 10 | AT16: =IF($AU16="","",SUBSTITUTE(SUBSTITUTE(SUBSTITUTE(SUBSTITUTE($AU16,IF($AW16="","",$AW16),IF($AW16="","",CONCATENATE("<color=#FFCC71>",$AW16,"</color>"))),IF($AX16="","",$AX16),IF($AX16="","",CONCATENATE("<color=#FFCC71>",$AX16,"</color>"))),IF($AY16="","",$AY16),IF($AY16="","",CONCATENATE("<color=#FFCC71>",$AY16,"</color>"))),IF($AZ16="","",$AZ16),IF($AZ16="","",CONCATENATE("<color=#FFCC71>",$AZ16,"</color>")))) -> 外敌当前，你们这些人不想着为祖国效力，竟然还打劫自己人！ | AU16: 外敌当前，你们这些人不想着为祖国效力，竟然还打劫自己人！
A17: 10003 | C17: =IF(A17=A16,C16+1,1) -> 1 | E17: DEMO | F17: =VLOOKUP(G17,'#TID_base_up'!B:C,2,0) -> 德·梅斯 | G17: TID_DialogueConf_10003_name_CN_Main | H17: icon_guidechara.smash | I17: =VLOOKUP(F17,'#Sheet1'!$J$2:$L$10,2,FALSE) -> frame_s_xsdh_003 | J17: TID_DialogueConf_10003_textList_CN_Main | T17: 1 | U17: 2 | V17: 0 | X17: 1005 | AD17: 2.35 | AE17: 3.35 | AH17: 0.1 | AL17: 10 | AT17: =IF($AU17="","",SUBSTITUTE(SUBSTITUTE(SUBSTITUTE(SUBSTITUTE($AU17,IF($AW17="","",$AW17),IF($AW17="","",CONCATENATE("<color=#FFCC71>",$AW17,"</color>"))),IF($AX17="","",$AX17),IF($AX17="","",CONCATENATE("<color=#FFCC71>",$AX17,"</color>"))),IF($AY17="","",$AY17),IF($AY17="","",CONCATENATE("<color=#FFCC71>",$AY17,"</color>"))),IF($AZ17="","",$AZ17),IF($AZ17="","",CONCATENATE("<color=#FFCC71>",$AZ17,"</color>")))) -> 我就说要迟到了…… | AU17: 我就说要迟到了……
A18: 10003 | C18: =IF(A18=A17,C17+1,1) -> 2 | E18: DEMO | F18: =VLOOKUP(G18,'#TID_base_up'!B:C,2,0) -> 伯特兰 | G18: TID_DialogueConf_10003_name_332050718590_CN_Main | H18: icon_guidechara.smash | I18: =VLOOKUP(F18,'#Sheet1'!$J$2:$L$10,2,FALSE) -> frame_s_xsdh_006 | J18: TID_DialogueConf_10003_textList_236019767422_CN_Main | T18: 1 | U18: 2 | V18: 0 | X18: 1005 | AD18: 5.8 | AE18: 6.8 | AH18: 0.1 | AL18: 10 | AT18: =IF($AU18="","",SUBSTITUTE(SUBSTITUTE(SUBSTITUTE(SUBSTITUTE($AU18,IF($AW18="","",$AW18),IF($AW18="","",CONCATENATE("<color=#FFCC71>",$AW18,"</color>"))),IF($AX18="","",$AX18),IF($AX18="","",CONCATENATE("<color=#FFCC71>",$AX18,"</color>"))),IF($AY18="","",$AY18),IF($AY18="","",CONCATENATE("<color=#FFCC71>",$AY18,"</color>"))),IF($AZ18="","",$AZ18),IF($AZ18="","",CONCATENATE("<color=#FFCC71>",$AZ18,"</color>")))) -> 别废话了！快救人！ | AU18: 别废话了！快救人！
A19: 10004 | C19: =IF(A19=A18,C18+1,1) -> 1 | E19: DEMO | F19: =VLOOKUP(G19,'#TID_base_up'!B:C,2,0) -> 伯特兰 | G19: TID_DialogueConf_10003_name_332050718590_CN_Main | H19: icon_guidechara.smash | I19: =VLOOKUP(F19,'#Sheet1'!$J$2:$L$10,2,FALSE) -> frame_s_xsdh_006 | J19: TID_DialogueConf_10004_textList_CN_Main | T19: 1 | U19: 2 | V19: 0 | X19: 1005 | AD19: 3.4 | AE19: 4.4 | AH19: 0.1 | AL19: 10 | AT19: =IF($AU19="","",SUBSTITUTE(SUBSTITUTE(SUBSTITUTE(SUBSTITUTE($AU19,IF($AW19="","",$AW19),IF($AW19="","",CONCATENATE("<color=#FFCC71>",$AW19,"</color>"))),IF($AX19="","",$AX19),IF($AX19="","",CONCATENATE("<color=#FFCC71>",$AX19,"</color>"))),IF($AY19="","",$AY19),IF($AY19="","",CONCATENATE("<color=#FFCC71>",$AY19,"</color>"))),IF($AZ19="","",$AZ19),IF($AZ19="","",CONCATENATE("<color=#FFCC71>",$AZ19,"</color>")))) -> 将部队拖拽向敌人，可以发起攻击。 | AU19: 将部队拖拽向敌人，可以发起攻击。
A20: 10005 | C20: =IF(A20=A19,C19+1,1) -> 1 | E20: DEMO | F20: =VLOOKUP(G20,'#TID_base_up'!B:C,2,0) -> 伯特兰 | G20: TID_DialogueConf_10003_name_332050718590_CN_Main | H20: icon_guidechara.smash | I20: =VLOOKUP(F20,'#Sheet1'!$J$2:$L$10,2,FALSE) -> frame_s_xsdh_006 | J20: TID_DialogueConf_10005_textList_CN_Main | T20: 1 | U20: 2 | V20: 0 | X20: 1005 | AD20: 2.8 | AE20: 3.8 | AH20: 0.1 | AL20: 10 | AT20: =IF($AU20="","",SUBSTITUTE(SUBSTITUTE(SUBSTITUTE(SUBSTITUTE($AU20,IF($AW20="","",$AW20),IF($AW20="","",CONCATENATE("<color=#FFCC71>",$AW20,"</color>"))),IF($AX20="","",$AX20),IF($AX20="","",CONCATENATE("<color=#FFCC71>",$AX20,"</color>"))),IF($AY20="","",$AY20),IF($AY20="","",CONCATENATE("<color=#FFCC71>",$AY20,"</color>"))),IF($AZ20="","",$AZ20),IF($AZ20="","",CONCATENATE("<color=#FFCC71>",$AZ20,"</color>")))) -> 你好，琼恩，我是伯特兰。 | AU20: 你好，琼恩，我是伯特兰。
A21: 10005 | C21: =IF(A21=A20,C20+1,1) -> 2 | E21: DEMO | F21: =VLOOKUP(G21,'#TID_base_up'!B:C,2,0) -> 德·梅斯 | G21: TID_DialogueConf_10003_name_CN_Main | H21: icon_guidechara.smash | I21: =VLOOKUP(F21,'#Sheet1'!$J$2:$L$10,2,FALSE) -> frame_s_xsdh_003 | J21: TID_DialogueConf_10005_textList_571453909965_CN_Main | T21: 1 | U21: 2 | V21: 0 | X21: 1005 | AD21: 3.7 | AE21: 4.7 | AH21: 0.1 | AL21: 10 | AT21: =IF($AU21="","",SUBSTITUTE(SUBSTITUTE(SUBSTITUTE(SUBSTITUTE($AU21,IF($AW21="","",$AW21),IF($AW21="","",CONCATENATE("<color=#FFCC71>",$AW21,"</color>"))),IF($AX21="","",$AX21),IF($AX21="","",CONCATENATE("<color=#FFCC71>",$AX21,"</color>"))),IF($AY21="","",$AY21),IF($AY21="","",CONCATENATE("<color=#FFCC71>",$AY21,"</color>"))),IF($AZ21="","",$AZ21),IF($AZ21="","",CONCATENATE("<color=#FFCC71>",$AZ21,"</color>")))) -> 让·德·梅斯，很荣幸为您效劳，女士。 | AU21: 让·德·梅斯，很荣幸为您效劳，女士。
A22: 10005 | C22: =IF(A22=A21,C21+1,1) -> 3 | E22: DEMO | F22: =VLOOKUP(G22,'#TID_base_up'!B:C,2,0) -> 伯特兰 | G22: TID_DialogueConf_10003_name_332050718590_CN_Main | H22: icon_guidechara.smash | I22: =VLOOKUP(F22,'#Sheet1'!$J$2:$L$10,2,FALSE) -> frame_s_xsdh_006 | J22: TID_DialogueConf_10005_textList_26062455831_CN_Main | T22: 1 | U22: 2 | V22: 0 | X22: 1005 | AD22: 5.05 | AE22: 6.05 | AH22: 0.1 | AL22: 10 | AT22: =IF($AU22="","",SUBSTITUTE(SUBSTITUTE(SUBSTITUTE(SUBSTITUTE($AU22,IF($AW22="","",$AW22),IF($AW22="","",CONCATENATE("<color=#FFCC71>",$AW22,"</color>"))),IF($AX22="","",$AX22),IF($AX22="","",CONCATENATE("<color=#FFCC71>",$AX22,"</color>"))),IF($AY22="","",$AY22),IF($AY22="","",CONCATENATE("<color=#FFCC71>",$AY22,"</color>"))),IF($AZ22="","",$AZ22),IF($AZ22="","",CONCATENATE("<color=#FFCC71>",$AZ22,"</color>")))) -> 我和梅斯会一同护送你到前往齐侬，皇太子正在那里等着你。 | AU22: 我和梅斯会一同护送你到前往齐侬，皇太子正在那里等着你。
A23: 10006 | C23: =IF(A23=A22,C22+1,1) -> 1 | E23: DEMO | F23: =VLOOKUP(G23,'#TID_base_up'!B:C,2,0) -> 强盗伏兵 | G23: TID_DialogueConf_10006_name_CN_Main | H23: icon_guidechara.smash | I23: =VLOOKUP(F23,'#Sheet1'!$J$2:$L$10,2,FALSE) -> frame_s_xsdh_005 | J23: TID_DialogueConf_10006_textList_CN_Main | T23: 1 | U23: 2 | V23: 0 | X23: 1005 | AD23: 2.2 | AE23: 3.2 | AH23: 0.1 | AL23: 10 | AT23: =IF($AU23="","",SUBSTITUTE(SUBSTITUTE(SUBSTITUTE(SUBSTITUTE($AU23,IF($AW23="","",$AW23),IF($AW23="","",CONCATENATE("<color=#FFCC71>",$AW23,"</color>"))),IF($AX23="","",$AX23),IF($AX23="","",CONCATENATE("<color=#FFCC71>",$AX23,"</color>"))),IF($AY23="","",$AY23),IF($AY23="","",CONCATENATE("<color=#FFCC71>",$AY23,"</color>"))),IF($AZ23="","",$AZ23),IF($AZ23="","",CONCATENATE("<color=#FFCC71>",$AZ23,"</color>")))) -> 肥鸭子送上门啦！ | AU23: 肥鸭子送上门啦！
A24: 10007 | C24: =IF(A24=A23,C23+1,1) -> 1 | E24: DEMO | F24: =VLOOKUP(G24,'#TID_base_up'!B:C,2,0) -> 勃艮第人 | G24: TID_DialogueConf_10007_name_CN_Main | H24: icon_guidechara.smash | I24: =VLOOKUP(F24,'#Sheet1'!$J$2:$L$10,2,FALSE) -> frame_s_xsdh_005 | J24: TID_DialogueConf_10007_textList_CN_Main | T24: 1 | U24: 2 | V24: 0 | X24: 1005 | AD24: 3.85 | AE24: 4.85 | AH24: 0.1 | AL24: 10 | AT24: =IF($AU24="","",SUBSTITUTE(SUBSTITUTE(SUBSTITUTE(SUBSTITUTE($AU24,IF($AW24="","",$AW24),IF($AW24="","",CONCATENATE("<color=#FFCC71>",$AW24,"</color>"))),IF($AX24="","",$AX24),IF($AX24="","",CONCATENATE("<color=#FFCC71>",$AX24,"</color>"))),IF($AY24="","",$AY24),IF($AY24="","",CONCATENATE("<color=#FFCC71>",$AY24,"</color>"))),IF($AZ24="","",$AZ24),IF($AZ24="","",CONCATENATE("<color=#FFCC71>",$AZ24,"</color>")))) -> 你们法兰西人就是不知道什么时候该认输！ | AU24: 你们法兰西人就是不知道什么时候该认输！
A25: 10008 | C25: =IF(A25=A24,C24+1,1) -> 1 | E25: DEMO | F25: =VLOOKUP(G25,'#TID_base_up'!B:C,2,0) -> 伯特兰 | G25: TID_DialogueConf_10003_name_332050718590_CN_Main | H25: icon_guidechara.smash | I25: =VLOOKUP(F25,'#Sheet1'!$J$2:$L$10,2,FALSE) -> frame_s_xsdh_006 | J25: TID_DialogueConf_10008_textList_CN_Main | T25: 1 | U25: 2 | V25: 0 | X25: 1005 | AD25: 3.25 | AE25: 4.25 | AH25: 0.1 | AL25: 10 | AT25: =IF($AU25="","",SUBSTITUTE(SUBSTITUTE(SUBSTITUTE(SUBSTITUTE($AU25,IF($AW25="","",$AW25),IF($AW25="","",CONCATENATE("<color=#FFCC71>",$AW25,"</color>"))),IF($AX25="","",$AX25),IF($AX25="","",CONCATENATE("<color=#FFCC71>",$AX25,"</color>"))),IF($AY25="","",$AY25),IF($AY25="","",CONCATENATE("<color=#FFCC71>",$AY25,"</color>"))),IF($AZ25="","",$AZ25),IF($AZ25="","",CONCATENATE("<color=#FFCC71>",$AZ25,"</color>")))) -> 解救友军能够增强部队的战斗力。 | AU25: 解救友军能够增强部队的战斗力。
A26: 10008 | C26: =IF(A26=A25,C25+1,1) -> 2 | E26: DEMO | F26: =VLOOKUP(G26,'#TID_base_up'!B:C,2,0) -> 德·梅斯 | G26: TID_DialogueConf_10003_name_CN_Main | H26: icon_guidechara.smash | I26: =VLOOKUP(F26,'#Sheet1'!$J$2:$L$10,2,FALSE) -> frame_s_xsdh_003 | J26: TID_DialogueConf_10008_textList_10977554256_CN_Main | T26: 1 | U26: 2 | V26: 0 | X26: 1005 | AD26: 4.3 | AE26: 5.3 | AH26: 0.1 | AL26: 10 | AT26: =IF($AU26="","",SUBSTITUTE(SUBSTITUTE(SUBSTITUTE(SUBSTITUTE($AU26,IF($AW26="","",$AW26),IF($AW26="","",CONCATENATE("<color=#FFCC71>",$AW26,"</color>"))),IF($AX26="","",$AX26),IF($AX26="","",CONCATENATE("<color=#FFCC71>",$AX26,"</color>"))),IF($AY26="","",$AY26),IF($AY26="","",CONCATENATE("<color=#FFCC71>",$AY26,"</color>"))),IF($AZ26="","",$AZ26),IF($AZ26="","",CONCATENATE("<color=#FFCC71>",$AZ26,"</color>")))) -> 同时也会将琼恩置于危险境地，两难呐，两难…… | AU26: 同时也会将琼恩置于危险境地，两难呐，两难……
A27: 10009 | C27: =IF(A27=A26,C26+1,1) -> 1 | E27: DEMO | F27: =VLOOKUP(G27,'#TID_base_up'!B:C,2,0) -> 伯特兰 | G27: TID_DialogueConf_10003_name_332050718590_CN_Main | H27: icon_guidechara.smash | I27: =VLOOKUP(F27,'#Sheet1'!$J$2:$L$10,2,FALSE) -> frame_s_xsdh_006 | J27: TID_DialogueConf_10009_textList_CN_Main | T27: 1 | U27: 2 | V27: 0 | X27: 1005 | AD27: 3.25 | AE27: 4.25 | AH27: 0.1 | AL27: 10 | AT27: =IF($AU27="","",SUBSTITUTE(SUBSTITUTE(SUBSTITUTE(SUBSTITUTE($AU27,IF($AW27="","",$AW27),IF($AW27="","",CONCATENATE("<color=#FFCC71>",$AW27,"</color>"))),IF($AX27="","",$AX27),IF($AX27="","",CONCATENATE("<color=#FFCC71>",$AX27,"</color>"))),IF($AY27="","",$AY27),IF($AY27="","",CONCATENATE("<color=#FFCC71>",$AY27,"</color>"))),IF($AZ27="","",$AZ27),IF($AZ27="","",CONCATENATE("<color=#FFCC71>",$AZ27,"</color>")))) -> 齐侬的朋友，我们一起并肩作战！ | AU27: 齐侬的朋友，我们一起并肩作战！
A28: 10009 | C28: =IF(A28=A27,C27+1,1) -> 2 | E28: DEMO | F28: =VLOOKUP(G28,'#TID_base_up'!B:C,2,0) -> 齐侬巡逻队 | G28: TID_DialogueConf_10009_name_902916305739_CN_Main | H28: icon_guidechara.smash | I28: =VLOOKUP(F28,'#Sheet1'!$J$2:$L$10,2,FALSE) -> frame_s_xsdh_002 | J28: TID_DialogueConf_10009_textList_148802160042_CN_Main | T28: 1 | U28: 2 | V28: 0 | X28: 1005 | AD28: 2.35 | AE28: 3.35 | AH28: 0.1 | AL28: 10 | AT28: =IF($AU28="","",SUBSTITUTE(SUBSTITUTE(SUBSTITUTE(SUBSTITUTE($AU28,IF($AW28="","",$AW28),IF($AW28="","",CONCATENATE("<color=#FFCC71>",$AW28,"</color>"))),IF($AX28="","",$AX28),IF($AX28="","",CONCATENATE("<color=#FFCC71>",$AX28,"</color>"))),IF($AY28="","",$AY28),IF($AY28="","",CONCATENATE("<color=#FFCC71>",$AY28,"</color>"))),IF($AZ28="","",$AZ28),IF($AZ28="","",CONCATENATE("<color=#FFCC71>",$AZ28,"</color>")))) -> 是友军！友军来了！ | AU28: 是友军！友军来了！
... A60: 10024 | C60: =IF(A60=A59,C59+1,1) -> 2 | E60: DEMO | F60: =VLOOKUP(G60,'#TID_base_up'!B:C,2,0) -> 德·梅斯 | G60: TID_DialogueConf_10003_name_CN_Main | H60: icon_guidechara.smash | I60: =VLOOKUP(F60,'#Sheet1'!$J$2:$L$10,2,FALSE) -> frame_s_xsdh_003 | J60: TID_DialogueConf_10024_textList_290367274068_CN_Main | T60: 1 | U60: 2 | V60: 0 | X60: 1005 | AD60: 5.2 | AE60: 6.2 | AH60: 0.1 | AL60: 10 | AT60: =IF($AU60="","",SUBSTITUTE(SUBSTITUTE(SUBSTITUTE(SUBSTITUTE($AU60,IF($AW60="","",$AW60),IF($AW60="","",CONCATENATE("<color=#FFCC71>",$AW60,"</color>"))),IF($AX60="","",$AX60),IF($AX60="","",CONCATENATE("<color=#FFCC71>",$AX60,"</color>"))),IF($AY60="","",$AY60),IF($AY60="","",CONCATENATE("<color=#FFCC71>",$AY60,"</color>"))),IF($AZ60="","",$AZ60),IF($AZ60="","",CONCATENATE("<color=#FFCC71>",$AZ60,"</color>")))) -> 攻击强盗可以吸引他们火力。如果琼恩倒下了，大家都得完蛋。 | AU60: 攻击强盗可以吸引他们火力。如果琼恩倒下了，大家都得完蛋。
A61: 11001 | C61: =IF(A61=A60,C60+1,1) -> 1 | E61: DEMO | F61: =VLOOKUP(G61,'#TID_base_up'!B:C,2,0) -> 琼恩 | G61: TID_DialogueConf_10001_name_CN_Main | H61: icon_guidechara.smash | I61: frame_s_xsdh_001 | J61: TID_DialogueConf_11001_textList_CN_Main | T61: 1 | U61: 2 | V61: 0 | X61: 1006 | Y61: FALSE | Z61: Play_voice_campaign_demo00_02_Jeanne | AA61: FALSE | AD61: 2.977083 | AE61: 3.98 | AH61: 0.1 | AL61: 10 | AT61: =IF($AU61="","",SUBSTITUTE(SUBSTITUTE(SUBSTITUTE(SUBSTITUTE($AU61,IF($AW61="","",$AW61),IF($AW61="","",CONCATENATE("<color=#FFCC71>",$AW61,"</color>"))),IF($AX61="","",$AX61),IF($AX61="","",CONCATENATE("<color=#FFCC71>",$AX61,"</color>"))),IF($AY61="","",$AY61),IF($AY61="","",CONCATENATE("<color=#FFCC71>",$AY61,"</color>"))),IF($AZ61="","",$AZ61),IF($AZ61="","",CONCATENATE("<color=#FFCC71>",$AZ61,"</color>")))) -> 说好了在这里会合，怎么到现在都不见人影？ | AU61: 说好了在这里会合，怎么到现在都不见人影？
A62: 11001 | C62: =IF(A62=A61,C61+1,1) -> 2 | E62: DEMO | F62: =VLOOKUP(G62,'#TID_base_up'!B:C,2,0) -> 强盗 | G62: TID_DialogueConf_10002_name_CN_Main | H62: icon_guidechara.smash | I62: frame_s_xsdh_005 | J62: TID_DialogueConf_10002_textList_CN_Main | T62: 1 | U62: 2 | V62: 0 | X62: 1006 | Y62: TRUE | Z62: Play_voice_campaign_demo00_03_Bandit | AA62: FALSE | AD62: 3.7119999 | AE62: 4.71 | AH62: 0.1 | AL62: 10 | AT62: =IF($AU62="","",SUBSTITUTE(SUBSTITUTE(SUBSTITUTE(SUBSTITUTE($AU62,IF($AW62="","",$AW62),IF($AW62="","",CONCATENATE("<color=#FFCC71>",$AW62,"</color>"))),IF($AX62="","",$AX62),IF($AX62="","",CONCATENATE("<color=#FFCC71>",$AX62,"</color>"))),IF($AY62="","",$AY62),IF($AY62="","",CONCATENATE("<color=#FFCC71>",$AY62,"</color>"))),IF($AZ62="","",$AZ62),IF($AZ62="","",CONCATENATE("<color=#FFCC71>",$AZ62,"</color>")))) -> 喂！女人！快把值钱的东西全部交出来！ | AU62: 喂！女人！快把值钱的东西全部交出来！
A63: 11001 | C63: =IF(A63=A62,C62+1,1) -> 3 | E63: DEMO | F63: =VLOOKUP(G63,'#TID_base_up'!B:C,2,0) -> 琼恩 | G63: TID_DialogueConf_10001_name_CN_Main | H63: icon_guidechara.smash | I63: frame_s_xsdh_001 | J63: TID_DialogueConf_11001_textList_882144978695_CN_Main | T63: 1 | U63: 2 | V63: 0 | X63: 1006 | Y63: FALSE | Z63: Play_voice_campaign_demo00_04_Jeanne | AA63: FALSE | AD63: 4.4613328 | AE63: 5.46 | AH63: 0.1 | AL63: 10 | AT63: =IF($AU63="","",SUBSTITUTE(SUBSTITUTE(SUBSTITUTE(SUBSTITUTE($AU63,IF($AW63="","",$AW63),IF($AW63="","",CONCATENATE("<color=#FFCC71>",$AW63,"</color>"))),IF($AX63="","",$AX63),IF($AX63="","",CONCATENATE("<color=#FFCC71>",$AX63,"</color>"))),IF($AY63="","",$AY63),IF($AY63="","",CONCATENATE("<color=#FFCC71>",$AY63,"</color>"))),IF($AZ63="","",$AZ63),IF($AZ63="","",CONCATENATE("<color=#FFCC71>",$AZ63,"</color>")))) -> 国难当头，你们还在打劫同胞！真是法兰西的耻辱！ | AU63: 国难当头，你们还在打劫同胞！真是法兰西的耻辱！
A64: 11001 | C64: =IF(A64=A63,C63+1,1) -> 4 | E64: DEMO | F64: =VLOOKUP(G64,'#TID_base_up'!B:C,2,0) -> 伯特兰 | G64: TID_DialogueConf_10003_name_332050718590_CN_Main | H64: icon_guidechara.smash | I64: frame_s_xsdh_006 | J64: TID_DialogueConf_11001_textList_54802890190_CN_Main | T64: 1 | U64: 2 | V64: 0 | X64: 1006 | Y64: TRUE | Z64: Play_voice_campaign_demo00_05_Bertrand | AA64: FALSE | AD64: 1.133333 | AE64: 2.13 | AH64: 0.1 | AL64: 10 | AT64: =IF($AU64="","",SUBSTITUTE(SUBSTITUTE(SUBSTITUTE(SUBSTITUTE($AU64,IF($AW64="","",$AW64),IF($AW64="","",CONCATENATE("<color=#FFCC71>",$AW64,"</color>"))),IF($AX64="","",$AX64),IF($AX64="","",CONCATENATE("<color=#FFCC71>",$AX64,"</color>"))),IF($AY64="","",$AY64),IF($AY64="","",CONCATENATE("<color=#FFCC71>",$AY64,"</color>"))),IF($AZ64="","",$AZ64),IF($AZ64="","",CONCATENATE("<color=#FFCC71>",$AZ64,"</color>")))) -> 说得好，琼恩！ | AU64: 说得好，琼恩！
A65: 11002 | C65: =IF(A65=A64,C64+1,1) -> 1 | E65: DEMO | F65: =VLOOKUP(G65,'#TID_base_up'!B:C,2,0) -> 伯特兰 | G65: TID_DialogueConf_10003_name_332050718590_CN_Main | H65: icon_guidechara.smash | I65: frame_s_xsdh_006 | J65: TID_DialogueConf_11002_textList_CN_Main | T65: 1 | U65: 2 | V65: 0 | X65: 1006 | Y65: FALSE | Z65: Play_voice_campaign_demo00_06_tips_Bertrand | AA65: FALSE | AD65: 2.622 | AE65: 3.62 | AH65: 0.1 | AL65: 10 | AT65: =IF($AU65="","",SUBSTITUTE(SUBSTITUTE(SUBSTITUTE(SUBSTITUTE($AU65,IF($AW65="","",$AW65),IF($AW65="","",CONCATENATE("<color=#FFCC71>",$AW65,"</color>"))),IF($AX65="","",$AX65),IF($AX65="","",CONCATENATE("<color=#FFCC71>",$AX65,"</color>"))),IF($AY65="","",$AY65),IF($AY65="","",CONCATENATE("<color=#FFCC71>",$AY65,"</color>"))),IF($AZ65="","",$AZ65),IF($AZ65="","",CONCATENATE("<color=#FFCC71>",$AZ65,"</color>")))) -> 将部队拖拽向敌人，立即发起攻击。 | AU65: 将部队拖拽向敌人，立即发起攻击。
A66: 11003 | C66: =IF(A66=A65,C65+1,1) -> 1 | E66: DEMO | F66: =VLOOKUP(G66,'#TID_base_up'!B:C,2,0) -> 琼恩 | G66: TID_DialogueConf_10001_name_CN_Main | H66: icon_guidechara.smash | I66: frame_s_xsdh_001 | J66: TID_DialogueConf_11003_textList_CN_Main | T66: 1 | U66: 3 | V66: 0 | X66: 1006 | Y66: TRUE | Z66: Play_voice_campaign_demo00_07_bubble_Jeanne | AA66: FALSE | AD66: 1.425 | AE66: 2.42 | AH66: 0.1 | AL66: 10 | AT66: =IF($AU66="","",SUBSTITUTE(SUBSTITUTE(SUBSTITUTE(SUBSTITUTE($AU66,IF($AW66="","",$AW66),IF($AW66="","",CONCATENATE("<color=#FFCC71>",$AW66,"</color>"))),IF($AX66="","",$AX66),IF($AX66="","",CONCATENATE("<color=#FFCC71>",$AX66,"</color>"))),IF($AY66="","",$AY66),IF($AY66="","",CONCATENATE("<color=#FFCC71>",$AY66,"</color>"))),IF($AZ66="","",$AZ66),IF($AZ66="","",CONCATENATE("<color=#FFCC71>",$AZ66,"</color>")))) -> 伯特兰！你迟到了。 | AU66: 伯特兰！你迟到了。
A67: 11004 | C67: =IF(A67=A66,C66+1,1) -> 1 | E67: DEMO | F67: =VLOOKUP(G67,'#TID_base_up'!B:C,2,0) -> 伯特兰 | G67: TID_DialogueConf_10003_name_332050718590_CN_Main | H67: icon_guidechara.smash | I67: frame_s_xsdh_006 | J67: TID_DialogueConf_11004_textList_CN_Main | T67: 1 | U67: 3 | V67: 0 | X67: 1006 | Y67: FALSE | Z67: Play_voice_campaign_demo00_08_bubble_Bertrand | AA67: FALSE | AD67: 4.6079998 | AE67: 5.61 | AH67: 0.1 | AL67: 10 | AT67: =IF($AU67="","",SUBSTITUTE(SUBSTITUTE(SUBSTITUTE(SUBSTITUTE($AU67,IF($AW67="","",$AW67),IF($AW67="","",CONCATENATE("<color=#FFCC71>",$AW67,"</color>"))),IF($AX67="","",$AX67),IF($AX67="","",CONCATENATE("<color=#FFCC71>",$AX67,"</color>"))),IF($AY67="","",$AY67),IF($AY67="","",CONCATENATE("<color=#FFCC71>",$AY67,"</color>"))),IF($AZ67="","",$AZ67),IF($AZ67="","",CONCATENATE("<color=#FFCC71>",$AZ67,"</color>")))) -> 请见谅，女士，路上遇到了一队英国佬，耽误了一点时间。 | AU67: 请见谅，女士，路上遇到了一队英国佬，耽误了一点时间。
A68: 11005 | C68: =IF(A68=A67,C67+1,1) -> 1 | E68: DEMO | F68: =VLOOKUP(G68,'#TID_base_up'!B:C,2,0) -> 伯特兰 | G68: TID_DialogueConf_10003_name_332050718590_CN_Main | H68: icon_guidechara.smash | I68: frame_s_xsdh_006 | J68: TID_DialogueConf_11005_textList_CN_Main | T68: 1 | U68: 2 | V68: 0 | X68: 1006 | Y68: FALSE | Z68: Play_voice_campaign_demo00_09_Bertrand | AA68: FALSE | AD68: 6.333333 | AE68: 7.33 | AH68: 0.1 | AL68: 10 | AT68: =IF($AU68="","",SUBSTITUTE(SUBSTITUTE(SUBSTITUTE(SUBSTITUTE($AU68,IF($AW68="","",$AW68),IF($AW68="","",CONCATENATE("<color=#FFCC71>",$AW68,"</color>"))),IF($AX68="","",$AX68),IF($AX68="","",CONCATENATE("<color=#FFCC71>",$AX68,"</color>"))),IF($AY68="","",$AY68),IF($AY68="","",CONCATENATE("<color=#FFCC71>",$AY68,"</color>"))),IF($AZ68="","",$AZ68),IF($AZ68="","",CONCATENATE("<color=#FFCC71>",$AZ68,"</color>")))) -> 皇太子正在齐侬等着，我和德·梅斯会护送你……等等……德·梅斯人呢？ | AU68: 皇太子正在齐侬等着，我和德·梅斯会护送你……等等……德·梅斯人呢？
A69: 11005 | C69: =IF(A69=A68,C68+1,1) -> 2 | E69: DEMO | F69: =VLOOKUP(G69,'#TID_base_up'!B:C,2,0) -> #N/A | G69: TID_DialogueConf_11005_name_286024863093_CN_Main | H69: icon_guidechara.smash | I69: frame_s_xsdh_001 | J69: TID_DialogueConf_11005_textList_118216904678_CN_Main | T69: 1 | U69: 2 | V69: 0 | X69: 1006 | Y69: FALSE | Z69: Play_voice_campaign_demo00_10_Jeanne | AA69: FALSE | AD69: 2.508333 | AE69: 3.51 | AH69: 0.1 | AL69: 10 | AT69: =IF($AU69="","",SUBSTITUTE(SUBSTITUTE(SUBSTITUTE(SUBSTITUTE($AU69,IF($AW69="","",$AW69),IF($AW69="","",CONCATENATE("<color=#FFCC71>",$AW69,"</color>"))),IF($AX69="","",$AX69),IF($AX69="","",CONCATENATE("<color=#FFCC71>",$AX69,"</color>"))),IF($AY69="","",$AY69),IF($AY69="","",CONCATENATE("<color=#FFCC71>",$AY69,"</color>"))),IF($AZ69="","",$AZ69),IF($AZ69="","",CONCATENATE("<color=#FFCC71>",$AZ69,"</color>")))) -> 他在前面探查，就等你过去会合了。 | AU69: 他在前面探查，就等你过去会合了。
A70: 11006 | C70: =IF(A70=A69,C69+1,1) -> 1 | E70: DEMO | F70: =VLOOKUP(G70,'#TID_base_up'!B:C,2,0) -> 强盗伏兵 | G70: TID_DialogueConf_10006_name_CN_Main | H70: icon_guidechara.smash | I70: frame_s_xsdh_005 | J70: TID_DialogueConf_11006_textList_CN_Main | T70: 1 | U70: 3 | V70: 0 | X70: 1006 | Y70: FALSE | Z70: Play_voice_campaign_demo00_11_bubble_BanditAmbush | AA70: FALSE | AD70: 3.573333 | AE70: 4.57 | AH70: 0.1 | AL70: 10 | AT70: =IF($AU70="","",SUBSTITUTE(SUBSTITUTE(SUBSTITUTE(SUBSTITUTE($AU70,IF($AW70="","",$AW70),IF($AW70="","",CONCATENATE("<color=#FFCC71>",$AW70,"</color>"))),IF($AX70="","",$AX70),IF($AX70="","",CONCATENATE("<color=#FFCC71>",$AX70,"</color>"))),IF($AY70="","",$AY70),IF($AY70="","",CONCATENATE("<color=#FFCC71>",$AY70,"</color>"))),IF($AZ70="","",$AZ70),IF($AZ70="","",CONCATENATE("<color=#FFCC71>",$AZ70,"</color>")))) -> 肥鸭子送上门了！ | AU70: 肥鸭子送上门了！
A71: 11007 | C71: =IF(A71=A70,C70+1,1) -> 1 | E71: DEMO | F71: =VLOOKUP(G71,'#TID_base_up'!B:C,2,0) -> 伯特兰 | G71: TID_DialogueConf_10003_name_332050718590_CN_Main | H71: icon_guidechara.smash | I71: frame_s_xsdh_006 | J71: TID_DialogueConf_11007_textList_CN_Main | T71: 1 | U71: 2 | V71: 0 | X71: 1006 | Y71: FALSE | Z71: Play_voice_campaign_demo00_12_Bertrand | AA71: FALSE | AD71: 5.5093331 | AE71: 6.51 | AH71: 0.1 | AL71: 10 | AT71: =IF($AU71="","",SUBSTITUTE(SUBSTITUTE(SUBSTITUTE(SUBSTITUTE($AU71,IF($AW71="","",$AW71),IF($AW71="","",CONCATENATE("<color=#FFCC71>",$AW71,"</color>"))),IF($AX71="","",$AX71),IF($AX71="","",CONCATENATE("<color=#FFCC71>",$AX71,"</color>"))),IF($AY71="","",$AY71),IF($AY71="","",CONCATENATE("<color=#FFCC71>",$AY71,"</color>"))),IF($AZ71="","",$AZ71),IF($AZ71="","",CONCATENATE("<color=#FFCC71>",$AZ71,"</color>")))) -> 攻击敌人可以吸引他们的火力。琼恩是我们最后的希望，决不能让她受到伤害！ | AU71: 攻击敌人可以吸引他们的火力。琼恩是我们最后的希望，决不能让她受到伤害！
A72: 11008 | C72: =IF(A72=A71,C71+1,1) -> 1 | E72: DEMO | F72: =VLOOKUP(G72,'#TID_base_up'!B:C,2,0) -> 伯特兰 | G72: TID_DialogueConf_10003_name_332050718590_CN_Main | H72: icon_guidechara.smash | I72: frame_s_xsdh_006 | J72: TID_DialogueConf_11008_textList_CN_Main | T72: 1 | U72: 2 | V72: 0 | X72: 1006 | Y72: FALSE | Z72: Play_voice_campaign_demo00_13_Bertrand | AA72: FALSE | AD72: 3.8453331 | AE72: 4.85 | AH72: 0.1 | AL72: 10 | AT72: =IF($AU72="","",SUBSTITUTE(SUBSTITUTE(SUBSTITUTE(SUBSTITUTE($AU72,IF($AW72="","",$AW72),IF($AW72="","",CONCATENATE("<color=#FFCC71>",$AW72,"</color>"))),IF($AX72="","",$AX72),IF($AX72="","",CONCATENATE("<color=#FFCC71>",$AX72,"</color>"))),IF($AY72="","",$AY72),IF($AY72="","",CONCATENATE("<color=#FFCC71>",$AY72,"</color>"))),IF($AZ72="","",$AZ72),IF($AZ72="","",CONCATENATE("<color=#FFCC71>",$AZ72,"</color>")))) -> 骑士克制弓兵！我们有绝对的优势！冲散他们！ | AU72: 骑士克制弓兵！我们有绝对的优势！冲散他们！
... A112: 11040 | C112: =IF(A112=A111,C111+1,1) -> 2 | E112: DEMO | F112: =VLOOKUP(G112,'#TID_base_up'!B:C,2,0) -> 德·梅斯 | G112: TID_DialogueConf_10003_name_CN_Main | H112: icon_guidechara.smash | I112: frame_s_xsdh_003 | J112: TID_DialogueConf_11040_textList_1027299844430_CN_Main | T112: 1 | U112: 2 | V112: 0 | X112: 1006 | Y112: FALSE | Z112: Play_voice_campaign_demo00_53_Mais | AA112: FALSE | AD112: 3.9946671 | AE112: 4.99 | AH112: 0.1 | AL112: 10 | AT112: =IF($AU112="","",SUBSTITUTE(SUBSTITUTE(SUBSTITUTE(SUBSTITUTE($AU112,IF($AW112="","",$AW112),IF($AW112="","",CONCATENATE("<color=#FFCC71>",$AW112,"</color>"))),IF($AX112="","",$AX112),IF($AX112="","",CONCATENATE("<color=#FFCC71>",$AX112,"</color>"))),IF($AY112="","",$AY112),IF($AY112="","",CONCATENATE("<color=#FFCC71>",$AY112,"</color>"))),IF($AZ112="","",$AZ112),IF($AZ112="","",CONCATENATE("<color=#FFCC71>",$AZ112,"</color>")))) -> 终于到了！齐侬的美酒在等我们！ | AU112: 终于到了！齐侬的美酒在等我们！
A113: 11041 | C113: 0 | E113: DEMO | F113: =VLOOKUP(G113,'#TID_base_up'!B:C,2,0) -> 剧情报幕开始 | G113: TID_DialogueConf_11041_name_CN_Main | J113: TID_DialogueConf_11041_textList_CN_Main | T113: 1 | U113: 0 | V113: 0 | X113: 1006 | Y113: FALSE | Z113: Play_voice_campaign_demo00_01_voiceover | AA113: FALSE | AD113: 13.4255 | AE113: 14.43 | AH113: 0.1 | AL113: 10 | AT113: =IF($AU113="","",SUBSTITUTE(SUBSTITUTE(SUBSTITUTE(SUBSTITUTE($AU113,IF($AW113="","",$AW113),IF($AW113="","",CONCATENATE("<color=#FFCC71>",$AW113,"</color>"))),IF($AX113="","",$AX113),IF($AX113="","",CONCATENATE("<color=#FFCC71>",$AX113,"</color>"))),IF($AY113="","",$AY113),IF($AY113="","",CONCATENATE("<color=#FFCC71>",$AY113,"</color>"))),IF($AZ113="","",$AZ113),IF($AZ113="","",CONCATENATE("<color=#FFCC71>",$AZ113,"</color>")))) -> 自阿金库尔战役惨败以来，英军几乎占领了法兰西的整个北部。 在民族存亡的巨大危机面前，一位普通的少女站了出来…… | AU113: 自阿金库尔战役惨败以来，英军几乎占领了法兰西的整个北部。 在民族存亡的巨大危机面前，一位普通的少女站了出来……
A114: 11042 | C114: 0 | E114: DEMO | F114: =VLOOKUP(G114,'#TID_base_up'!B:C,2,0) -> 剧情报幕结束 | G114: TID_DialogueConf_11042_name_CN_Main | J114: TID_DialogueConf_11042_textList_CN_Main | T114: 1 | U114: 0 | V114: 0 | X114: 1006 | Y114: FALSE | Z114: Play_voice_campaign_demo00_54_voiceover | AA114: FALSE | AD114: 14.938666 | AE114: 15.94 | AH114: 0.1 | AL114: 10 | AT114: =IF($AU114="","",SUBSTITUTE(SUBSTITUTE(SUBSTITUTE(SUBSTITUTE($AU114,IF($AW114="","",$AW114),IF($AW114="","",CONCATENATE("<color=#FFCC71>",$AW114,"</color>"))),IF($AX114="","",$AX114),IF($AX114="","",CONCATENATE("<color=#FFCC71>",$AX114,"</color>"))),IF($AY114="","",$AY114),IF($AY114="","",CONCATENATE("<color=#FFCC71>",$AY114,"</color>"))),IF($AZ114="","",$AZ114),IF($AZ114="","",CONCATENATE("<color=#FFCC71>",$AZ114,"</color>")))) -> 琼恩站在皇太子面前，周边的窃窃私语并没有让她感到惶恐，人们怀疑的目光也没有让她退缩。 因为她知道，自己就站在正确的道路之上。 | AU114: 琼恩站在皇太子面前，周边的窃窃私语并没有让她感到惶恐，人们怀疑的目光也没有让她退缩。 因为她知道，自己就站在正确的道路之上。
A115: 41001 | B115: 序章 | C115: 1 | D115: 新手序章 | E115: 国内S1 | F115: =VLOOKUP(G115,'#TID_base_up'!B:C,2,0) -> 尤里乌斯 | G115: TID_DialogueConf_41001_name_CN_Main | H115: =VLOOKUP($G115,'#对话模型配置'!$A:$W,MATCH(对话配置表!H$2,'#对话模型配置'!$1:$1,0)) -> altasPath | I115: =VLOOKUP($G115,'#对话模型配置'!$A:$W,MATCH(对话配置表!I$2,'#对话模型配置'!$1:$1,0)) -> picture | J115: TID_DialogueConf_41001_textList_CN_Main | K115: =AT115 -> 领主大人，<color=#FFCC71>城门已被蛮族攻破</color>！再不快点，陛下恐怕要不行了。 | T115: 1 | U115: 1 | V115: 0 | X115: 3 | Y115: FALSE | Z115: Play_voice_campaign_beginner00_04_Caesar | AA115: FALSE | AC115: 20001007 | AD115: 5.5626669 | AE115: 6.56 | AH115: 1.5 | AL115: 25 | AM115: =VLOOKUP($F115,'#对话模型配置'!$A:$W,MATCH(对话配置表!AM$2,'#对话模型配置'!$1:$1,0),FALSE) -> 20001003 | AN115: chapter_0_1 | AT115: =IF($AU115="","",SUBSTITUTE(SUBSTITUTE(SUBSTITUTE(SUBSTITUTE($AU115,IF($AW115="","",$AW115),IF($AW115="","",CONCATENATE("<color=#FFCC71>",$AW115,"</color>"))),IF($AX115="","",$AX115),IF($AX115="","",CONCATENATE("<color=#FFCC71>",$AX115,"</color>"))),IF($AY115="","",$AY115),IF($AY115="","",CONCATENATE("<color=#FFCC71>",$AY115,"</color>"))),IF($AZ115="","",$AZ115),IF($AZ115="","",CONCATENATE("<color=#FFCC71>",$AZ115,"</color>")))) -> 领主大人，<color=#FFCC71>城门已被蛮族攻破</color>！再不快点，陛下恐怕要不行了。 | AU115: 领主大人，城门已被蛮族攻破！再不快点，陛下恐怕要不行了。 | AW115: 城门已被蛮族攻破
A116: 41002 | B116: 序章 | C116: 1 | D116: 新手序章 | E116: 国内S1 | F116: =VLOOKUP(G116,'#TID_base_up'!B:C,2,0) -> 尤里乌斯 | G116: TID_DialogueConf_41001_name_CN_Main | H116: =VLOOKUP($G116,'#对话模型配置'!$A:$W,MATCH(对话配置表!H$2,'#对话模型配置'!$1:$1,0)) -> altasPath | I116: =VLOOKUP($G116,'#对话模型配置'!$A:$W,MATCH(对话配置表!I$2,'#对话模型配置'!$1:$1,0)) -> picture | J116: TID_DialogueConf_41002_textList_CN_Main | K116: =AT116 -> 这些<color=#FFCC71>野蛮人</color>竟然也懂得<color=#FFCC71>封锁道路</color>，看来是有两下子，我们得绕着走。 | T116: 1 | U116: 1 | V116: 0 | X116: 3 | Y116: FALSE | Z116: Play_voice_campaign_beginner00_06_Caesar | AA116: FALSE | AC116: 20001008 | AD116: 6.1680002 | AE116: 7.17 | AH116: 1.5 | AL116: 25 | AM116: =VLOOKUP($F116,'#对话模型配置'!$A:$W,MATCH(对话配置表!AM$2,'#对话模型配置'!$1:$1,0),FALSE) -> 20001003 | AN116: chapter_0_2 | AT116: =IF($AU116="","",SUBSTITUTE(SUBSTITUTE(SUBSTITUTE(SUBSTITUTE($AU116,IF($AW116="","",$AW116),IF($AW116="","",CONCATENATE("<color=#FFCC71>",$AW116,"</color>"))),IF($AX116="","",$AX116),IF($AX116="","",CONCATENATE("<color=#FFCC71>",$AX116,"</color>"))),IF($AY116="","",$AY116),IF($AY116="","",CONCATENATE("<color=#FFCC71>",$AY116,"</color>"))),IF($AZ116="","",$AZ116),IF($AZ116="","",CONCATENATE("<color=#FFCC71>",$AZ116,"</color>")))) -> 这些<color=#FFCC71>野蛮人</color>竟然也懂得<color=#FFCC71>封锁道路</color>，看来是有两下子，我们得绕着走。 | AU116: 这些野蛮人竟然也懂得封锁道路，看来是有两下子，我们得绕着走。 | AW116: 野蛮人 | AX116: 封锁道路
A117: 41003 | B117: 序章 | C117: 1 | D117: 新手序章 | E117: 国内S1 | F117: =VLOOKUP(G117,'#TID_base_up'!B:C,2,0) -> 帝国斥候 | G117: TID_DialogueConf_41003_name_CN_Main | H117: =VLOOKUP($G117,'#对话模型配置'!$A:$W,MATCH(对话配置表!H$2,'#对话模型配置'!$1:$1,0)) -> altasPath | I117: =VLOOKUP($G117,'#对话模型配置'!$A:$W,MATCH(对话配置表!I$2,'#对话模型配置'!$1:$1,0)) -> picture | J117: TID_DialogueConf_41003_textList_CN_Main | K117: =AT117 -> 放下武器，是友军！太好了，皇城有救了！ | T117: 1 | U117: 4 | V117: 0 | X117: 3 | Y117: TRUE | Z117: Play_voice_campaign_beginner00_09_bubble_Allies | AA117: FALSE | AD117: 4.4239998 | AE117: 5.42 | AH117: 0.1 | AL117: 25 | AO117: 2 | AQ117: 0;-100 | AT117: =IF($AU117="","",SUBSTITUTE(SUBSTITUTE(SUBSTITUTE(SUBSTITUTE($AU117,IF($AW117="","",$AW117),IF($AW117="","",CONCATENATE("<color=#FFCC71>",$AW117,"</color>"))),IF($AX117="","",$AX117),IF($AX117="","",CONCATENATE("<color=#FFCC71>",$AX117,"</color>"))),IF($AY117="","",$AY117),IF($AY117="","",CONCATENATE("<color=#FFCC71>",$AY117,"</color>"))),IF($AZ117="","",$AZ117),IF($AZ117="","",CONCATENATE("<color=#FFCC71>",$AZ117,"</color>")))) -> 放下武器，是友军！太好了，皇城有救了！ | AU117: 放下武器，是友军！太好了，皇城有救了！
A118: 41004 | B118: 序章 | C118: 1 | D118: 新手序章 | E118: 国内S1 | F118: =VLOOKUP(G118,'#TID_base_up'!B:C,2,0) -> 尤里乌斯 | G118: TID_DialogueConf_41001_name_CN_Main | H118: =VLOOKUP($G118,'#对话模型配置'!$A:$W,MATCH(对话配置表!H$2,'#对话模型配置'!$1:$1,0)) -> altasPath | I118: =VLOOKUP($G118,'#对话模型配置'!$A:$W,MATCH(对话配置表!I$2,'#对话模型配置'!$1:$1,0)) -> picture | J118: TID_DialogueConf_41004_textList_CN_Main | K118: =AT118 -> 战士们，跟上部队！陛下还在皇城等着我们！ | T118: 1 | U118: 4 | V118: 0 | X118: 3 | Y118: TRUE | Z118: Play_voice_campaign_beginner00_11_bubble_Caesar | AA118: FALSE | AD118: 5.2686672 | AE118: 6.27 | AH118: 0.1 | AL118: 25 | AO118: 1 | AT118: =IF($AU118="","",SUBSTITUTE(SUBSTITUTE(SUBSTITUTE(SUBSTITUTE($AU118,IF($AW118="","",$AW118),IF($AW118="","",CONCATENATE("<color=#FFCC71>",$AW118,"</color>"))),IF($AX118="","",$AX118),IF($AX118="","",CONCATENATE("<color=#FFCC71>",$AX118,"</color>"))),IF($AY118="","",$AY118),IF($AY118="","",CONCATENATE("<color=#FFCC71>",$AY118,"</color>"))),IF($AZ118="","",$AZ118),IF($AZ118="","",CONCATENATE("<color=#FFCC71>",$AZ118,"</color>")))) -> 战士们，跟上部队！陛下还在皇城等着我们！ | AU118: 战士们，跟上部队！陛下还在皇城等着我们！
A119: 41005 | B119: 序章 | C119: 1 | D119: 新手序章 | E119: 国内S1 | F119: =VLOOKUP(G119,'#TID_base_up'!B:C,2,0) -> 尤里乌斯 | G119: TID_DialogueConf_41001_name_CN_Main | H119: =VLOOKUP($G119,'#对话模型配置'!$A:$W,MATCH(对话配置表!H$2,'#对话模型配置'!$1:$1,0)) -> altasPath | I119: =VLOOKUP($G119,'#对话模型配置'!$A:$W,MATCH(对话配置表!I$2,'#对话模型配置'!$1:$1,0)) -> picture | J119: TID_DialogueConf_41005_textList_CN_Main | K119: =AT119 -> 除了<color=#FFCC71>硬刚</color>，没有其他可走的路了，就让我们这些士兵“热热身”，<color=#FFCC71>拔掉这个关隘</color>！ | T119: 1 | U119: 1 | V119: 0 | X119: 3 | Y119: TRUE | Z119: Play_voice_campaign_beginner00_12_Caesar | AA119: FALSE | AC119: 20001009 | AD119: 7.4248958 | AE119: 8.42 | AH119: 1.5 | AL119: 25 | AM119: =VLOOKUP($F119,'#对话模型配置'!$A:$W,MATCH(对话配置表!AM$2,'#对话模型配置'!$1:$1,0),FALSE) -> 20001003 | AN119: chapter_0_3 | AT119: =IF($AU119="","",SUBSTITUTE(SUBSTITUTE(SUBSTITUTE(SUBSTITUTE($AU119,IF($AW119="","",$AW119),IF($AW119="","",CONCATENATE("<color=#FFCC71>",$AW119,"</color>"))),IF($AX119="","",$AX119),IF($AX119="","",CONCATENATE("<color=#FFCC71>",$AX119,"</color>"))),IF($AY119="","",$AY119),IF($AY119="","",CONCATENATE("<color=#FFCC71>",$AY119,"</color>"))),IF($AZ119="","",$AZ119),IF($AZ119="","",CONCATENATE("<color=#FFCC71>",$AZ119,"</color>")))) -> 除了<color=#FFCC71>硬刚</color>，没有其他可走的路了，就让我们这些士兵“热热身”，<color=#FFCC71>拔掉这个关隘</color>！ | AU119: 除了硬刚，没有其他可走的路了，就让我们这些士兵“热热身”，拔掉这个关隘！ | AW119: 硬刚 | AX119: 拔掉这个关隘
A120: 41005 | B120: 序章 | C120: 2 | D120: 新手序章 | E120: 国内S1 | F120: =VLOOKUP(G120,'#TID_base_up'!B:C,2,0) -> 帝国斥候 | G120: TID_DialogueConf_41003_name_CN_Main | H120: =VLOOKUP($G120,'#对话模型配置'!$A:$W,MATCH(对话配置表!H$2,'#对话模型配置'!$1:$1,0)) -> altasPath | I120: =VLOOKUP($G120,'#对话模型配置'!$A:$W,MATCH(对话配置表!I$2,'#对话模型配置'!$1:$1,0)) -> picture | J120: TID_DialogueConf_41005_textList_834036336037_CN_Main | K120: =AT120 -> 禀告大人，<color=#FFCC71>关隘内部</color>存放了<color=#FFCC71>大量火药</color>，只要一点火花，就能把他们炸上天！ | T120: 1 | U120: 1 | V120: 0 | X120: 3 | Y120: FALSE | Z120: Play_voice_campaign_beginner00_13_Allies | AA120: FALSE | AC120: 20001010 | AD120: 5.5673332 | AE120: 6.57 | AH120: 1.5 | AL120: 25 | AM120: =VLOOKUP($F120,'#对话模型配置'!$A:$W,MATCH(对话配置表!AM$2,'#对话模型配置'!$1:$1,0),FALSE) -> 20001001 | AN120: chapter_0_4 | AT120: =IF($AU120="","",SUBSTITUTE(SUBSTITUTE(SUBSTITUTE(SUBSTITUTE($AU120,IF($AW120="","",$AW120),IF($AW120="","",CONCATENATE("<color=#FFCC71>",$AW120,"</color>"))),IF($AX120="","",$AX120),IF($AX120="","",CONCATENATE("<color=#FFCC71>",$AX120,"</color>"))),IF($AY120="","",$AY120),IF($AY120="","",CONCATENATE("<color=#FFCC71>",$AY120,"</color>"))),IF($AZ120="","",$AZ120),IF($AZ120="","",CONCATENATE("<color=#FFCC71>",$AZ120,"</color>")))) -> 禀告大人，<color=#FFCC71>关隘内部</color>存放了<color=#FFCC71>大量火药</color>，只要一点火花，就能把他们炸上天！ | AU120: 禀告大人，关隘内部存放了大量火药，只要一点火花，就能把他们炸上天！ | AW120: 关隘内部 | AX120: 大量火药
A121: 41006 | B121: 序章 | C121: 1 | D121: 新手序章 | E121: 国内S1 | F121: =VLOOKUP(G121,'#TID_base_up'!B:C,2,0) -> 尤里乌斯 | G121: TID_DialogueConf_41001_name_CN_Main | H121: =VLOOKUP($G121,'#对话模型配置'!$A:$W,MATCH(对话配置表!H$2,'#对话模型配置'!$1:$1,0)) -> altasPath | I121: =VLOOKUP($G121,'#对话模型配置'!$A:$W,MATCH(对话配置表!I$2,'#对话模型配置'!$1:$1,0)) -> picture | J121: TID_DialogueConf_41006_textList_CN_Main | K121: =AT121 -> 投石车，发射！让火药炸一会！ | T121: 1 | U121: 4 | V121: 1 | X121: 3 | Y121: TRUE | Z121: Play_voice_campaign_beginner00_17_bubble_Caesar | AA121: FALSE | AD121: 4.186666 | AE121: 5.19 | AH121: 0.1 | AL121: 25 | AO121: 1 | AT121: =IF($AU121="","",SUBSTITUTE(SUBSTITUTE(SUBSTITUTE(SUBSTITUTE($AU121,IF($AW121="","",$AW121),IF($AW121="","",CONCATENATE("<color=#FFCC71>",$AW121,"</color>"))),IF($AX121="","",$AX121),IF($AX121="","",CONCATENATE("<color=#FFCC71>",$AX121,"</color>"))),IF($AY121="","",$AY121),IF($AY121="","",CONCATENATE("<color=#FFCC71>",$AY121,"</color>"))),IF($AZ121="","",$AZ121),IF($AZ121="","",CONCATENATE("<color=#FFCC71>",$AZ121,"</color>")))) -> 投石车，发射！让火药炸一会！ | AU121: 投石车，发射！让火药炸一会！
A122: 41007 | B122: 序章 | C122: 1 | D122: 新手序章 | E122: 国内S1 | F122: =VLOOKUP(G122,'#TID_base_up'!B:C,2,0) -> 尤里乌斯 | G122: TID_DialogueConf_41001_name_CN_Main | H122: =VLOOKUP($G122,'#对话模型配置'!$A:$W,MATCH(对话配置表!H$2,'#对话模型配置'!$1:$1,0)) -> altasPath | I122: =VLOOKUP($G122,'#对话模型配置'!$A:$W,MATCH(对话配置表!I$2,'#对话模型配置'!$1:$1,0)) -> picture | J122: TID_DialogueConf_41007_textList_CN_Main | K122: =AT122 -> 利剑出鞘，随我冲锋！重铸荣光，我辈义不容辞！ | T122: 1 | U122: 4 | V122: 1 | X122: 3 | Y122: TRUE | Z122: Play_voice_campaign_beginner00_18_bubble_Caesar | AA122: TRUE | AD122: 6.7036881 | AE122: 7.7 | AH122: 0.1 | AL122: 25 | AO122: 1 | AQ122: 0;-60 | AT122: =IF($AU122="","",SUBSTITUTE(SUBSTITUTE(SUBSTITUTE(SUBSTITUTE($AU122,IF($AW122="","",$AW122),IF($AW122="","",CONCATENATE("<color=#FFCC71>",$AW122,"</color>"))),IF($AX122="","",$AX122),IF($AX122="","",CONCATENATE("<color=#FFCC71>",$AX122,"</color>"))),IF($AY122="","",$AY122),IF($AY122="","",CONCATENATE("<color=#FFCC71>",$AY122,"</color>"))),IF($AZ122="","",$AZ122),IF($AZ122="","",CONCATENATE("<color=#FFCC71>",$AZ122,"</color>")))) -> 利剑出鞘，随我冲锋！重铸荣光，我辈义不容辞！ | AU122: 利剑出鞘，随我冲锋！重铸荣光，我辈义不容辞！
A123: 41008 | B123: 序章 | C123: 1 | D123: 新手序章 | E123: 国内S1 | F123: =VLOOKUP(G123,'#TID_base_up'!B:C,2,0) -> 帝国斥候 | G123: TID_DialogueConf_41003_name_CN_Main | H123: =VLOOKUP($G123,'#对话模型配置'!$A:$W,MATCH(对话配置表!H$2,'#对话模型配置'!$1:$1,0)) -> altasPath | I123: =VLOOKUP($G123,'#对话模型配置'!$A:$W,MATCH(对话配置表!I$2,'#对话模型配置'!$1:$1,0)) -> picture | J123: TID_DialogueConf_41008_textList_CN_Main | K123: =AT123 -> 大人，敌人被打残了！快使用[主将技能]收割他们！ | T123: 1 | U123: 4 | V123: 2 | X123: 3 | Y123: TRUE | Z123: Play_voice_campaign_beginner00_19_bubble_Allies | AA123: TRUE | AD123: 4.1075001 | AE123: 5.11 | AH123: 0.1 | AL123: 25 | AO123: 1 | AQ123: 0;-60 | AT123: =IF($AU123="","",SUBSTITUTE(SUBSTITUTE(SUBSTITUTE(SUBSTITUTE($AU123,IF($AW123="","",$AW123),IF($AW123="","",CONCATENATE("<color=#FFCC71>",$AW123,"</color>"))),IF($AX123="","",$AX123),IF($AX123="","",CONCATENATE("<color=#FFCC71>",$AX123,"</color>"))),IF($AY123="","",$AY123),IF($AY123="","",CONCATENATE("<color=#FFCC71>",$AY123,"</color>"))),IF($AZ123="","",$AZ123),IF($AZ123="","",CONCATENATE("<color=#FFCC71>",$AZ123,"</color>")))) -> 大人，敌人被打残了！快使用[主将技能]收割他们！ | AU123: 大人，敌人被打残了！快使用[主将技能]收割他们！
A124: 41009 | B124: 序章 | C124: 1 | D124: 新手序章 | E124: 国内S1 | F124: =VLOOKUP(G124,'#TID_base_up'!B:C,2,0) -> 帝国斥候 | G124: TID_DialogueConf_41003_name_CN_Main | H124: =VLOOKUP($G124,'#对话模型配置'!$A:$W,MATCH(对话配置表!H$2,'#对话模型配置'!$1:$1,0)) -> altasPath | I124: =VLOOKUP($G124,'#对话模型配置'!$A:$W,MATCH(对话配置表!I$2,'#对话模型配置'!$1:$1,0)) -> picture | J124: TID_DialogueConf_41009_textList_CN_Main | K124: =AT124 -> 撑住！援军快要来了！ | T124: 1 | U124: 4 | V124: 1 | X124: 3 | Y124: FALSE | Z124: Play_voice_campaign_beginner00_20_1_tips_Soldier | AA124: FALSE | AD124: 2.994055 | AE124: 3.99 | AH124: 1.5 | AL124: 25 | AO124: 6 | AQ124: 0;-100 | AT124: =IF($AU124="","",SUBSTITUTE(SUBSTITUTE(SUBSTITUTE(SUBSTITUTE($AU124,IF($AW124="","",$AW124),IF($AW124="","",CONCATENATE("<color=#FFCC71>",$AW124,"</color>"))),IF($AX124="","",$AX124),IF($AX124="","",CONCATENATE("<color=#FFCC71>",$AX124,"</color>"))),IF($AY124="","",$AY124),IF($AY124="","",CONCATENATE("<color=#FFCC71>",$AY124,"</color>"))),IF($AZ124="","",$AZ124),IF($AZ124="","",CONCATENATE("<color=#FFCC71>",$AZ124,"</color>")))) -> 撑住！援军快要来了！ | AU124: 撑住！援军快要来了！ | AW124: 哨塔
A125: 41010 | B125: 序章 | C125: 1 | D125: 新手序章 | E125: 国内S1 | F125: =VLOOKUP(G125,'#TID_base_up'!B:C,2,0) -> 帝国斥候 | G125: TID_DialogueConf_41003_name_CN_Main | H125: =VLOOKUP($G125,'#对话模型配置'!$A:$W,MATCH(对话配置表!H$2,'#对话模型配置'!$1:$1,0)) -> altasPath | I125: =VLOOKUP($G125,'#对话模型配置'!$A:$W,MATCH(对话配置表!I$2,'#对话模型配置'!$1:$1,0)) -> picture | J125: TID_DialogueConf_41010_textList_CN_Main | K125: =AT125 -> 大人，保存实力，别正面刚，利用<color=#FFCC71>兵种克制</color>就可以轻松<color=#FFCC71>压制敌人</color>。 | T125: 1 | U125: 1 | V125: 0 | X125: 3 | Y125: TRUE | Z125: Play_voice_campaign_beginner00_21_Allies | AA125: FALSE | AC125: 20001011 | AD125: 5.941833 | AE125: 6.94 | AH125: 1.5 | AL125: 25 | AM125: =VLOOKUP($F125,'#对话模型配置'!$A:$W,MATCH(对话配置表!AM$2,'#对话模型配置'!$1:$1,0),FALSE) -> 20001001 | AN125: chapter_0_5 | AT125: =IF($AU125="","",SUBSTITUTE(SUBSTITUTE(SUBSTITUTE(SUBSTITUTE($AU125,IF($AW125="","",$AW125),IF($AW125="","",CONCATENATE("<color=#FFCC71>",$AW125,"</color>"))),IF($AX125="","",$AX125),IF($AX125="","",CONCATENATE("<color=#FFCC71>",$AX125,"</color>"))),IF($AY125="","",$AY125),IF($AY125="","",CONCATENATE("<color=#FFCC71>",$AY125,"</color>"))),IF($AZ125="","",$AZ125),IF($AZ125="","",CONCATENATE("<color=#FFCC71>",$AZ125,"</color>")))) -> 大人，保存实力，别正面刚，利用<color=#FFCC71>兵种克制</color>就可以轻松<color=#FFCC71>压制敌人</color>。 | AU125: 大人，保存实力，别正面刚，利用兵种克制就可以轻松压制敌人。 | AW125: 兵种克制 | AX125: 压制敌人
A126: 41011 | B126: 序章 | C126: 1 | D126: 新手序章 | E126: 国内S1 | F126: =VLOOKUP(G126,'#TID_base_up'!B:C,2,0) -> 帝国斥候 | G126: TID_DialogueConf_41003_name_CN_Main | H126: =VLOOKUP($G126,'#对话模型配置'!$A:$W,MATCH(对话配置表!H$2,'#对话模型配置'!$1:$1,0)) -> altasPath | I126: =VLOOKUP($G126,'#对话模型配置'!$A:$W,MATCH(对话配置表!I$2,'#对话模型配置'!$1:$1,0)) -> picture | J126: TID_DialogueConf_41011_textList_CN_Main | K126: =AT126 -> 占领这座哨塔，可以让我们的视野更加开阔。（目前没配置） | T126: 1 | U126: 1 | V126: 2 | X126: 3 | AA126: FALSE | AE126: 1 | AH126: 1.5 | AL126: 25 | AT126: =IF($AU126="","",SUBSTITUTE(SUBSTITUTE(SUBSTITUTE(SUBSTITUTE($AU126,IF($AW126="","",$AW126),IF($AW126="","",CONCATENATE("<color=#FFCC71>",$AW126,"</color>"))),IF($AX126="","",$AX126),IF($AX126="","",CONCATENATE("<color=#FFCC71>",$AX126,"</color>"))),IF($AY126="","",$AY126),IF($AY126="","",CONCATENATE("<color=#FFCC71>",$AY126,"</color>"))),IF($AZ126="","",$AZ126),IF($AZ126="","",CONCATENATE("<color=#FFCC71>",$AZ126,"</color>")))) -> 占领这座哨塔，可以让我们的视野更加开阔。（目前没配置） | AU126: 占领这座哨塔，可以让我们的视野更加开阔。（目前没配置）
A127: 41012 | B127: 序章 | C127: 1 | D127: 新手序章 | E127: 国内S1 | F127: =VLOOKUP(G127,'#TID_base_up'!B:C,2,0) -> 安德莉娅 | G127: TID_DialogueConf_2055001_name_CN_Main | H127: =VLOOKUP($G127,'#对话模型配置'!$A:$W,MATCH(对话配置表!H$2,'#对话模型配置'!$1:$1,0)) -> altasPath | I127: =VLOOKUP($G127,'#对话模型配置'!$A:$W,MATCH(对话配置表!I$2,'#对话模型配置'!$1:$1,0)) -> picture | J127: TID_DialogueConf_41012_textList_CN_Main | K127: =AT127 -> 老狗都有几颗牙，再看看你们，就这么点儿能耐吗？ | T127: 1 | U127: 4 | V127: 0 | X127: 3 | Y127: TRUE | Z127: Play_voice_campaign_beginner00_26_bubble_Andrea | AA127: FALSE | AD127: 5.0306668 | AE127: 6.03 | AH127: 0.1 | AL127: 25 | AO127: 17 | AQ127: -40;-70 | AT127: =IF($AU127="","",SUBSTITUTE(SUBSTITUTE(SUBSTITUTE(SUBSTITUTE($AU127,IF($AW127="","",$AW127),IF($AW127="","",CONCATENATE("<color=#FFCC71>",$AW127,"</color>"))),IF($AX127="","",$AX127),IF($AX127="","",CONCATENATE("<color=#FFCC71>",$AX127,"</color>"))),IF($AY127="","",$AY127),IF($AY127="","",CONCATENATE("<color=#FFCC71>",$AY127,"</color>"))),IF($AZ127="","",$AZ127),IF($AZ127="","",CONCATENATE("<color=#FFCC71>",$AZ127,"</color>")))) -> 老狗都有几颗牙，再看看你们，就这么点儿能耐吗？ | AU127: 老狗都有几颗牙，再看看你们，就这么点儿能耐吗？
A128: 41013 | B128: 序章 | C128: 1 | D128: 新手序章 | E128: 国内S1 | F128: =VLOOKUP(G128,'#TID_base_up'!B:C,2,0) -> 蛮族前锋 | G128: TID_DialogueConf_41013_name_CN_Main | H128: =VLOOKUP($G128,'#对话模型配置'!$A:$W,MATCH(对话配置表!H$2,'#对话模型配置'!$1:$1,0)) -> altasPath | I128: =VLOOKUP($G128,'#对话模型配置'!$A:$W,MATCH(对话配置表!I$2,'#对话模型配置'!$1:$1,0)) -> picture | J128: TID_DialogueConf_41013_textList_CN_Main | K128: =AT128 -> 牙尖嘴利，一会儿看我怎么收拾你！ | T128: 1 | U128: 4 | V128: 0 | X128: 3 | Y128: TRUE | Z128: Play_voice_campaign_beginner00_27_bubble_Barbarian | AA128: FALSE | AD128: 3.7093329 | AE128: 4.71 | AH128: 0.1 | AL128: 25 | AO128: 17 | AQ128: -30;-75 | AT128: =IF($AU128="","",SUBSTITUTE(SUBSTITUTE(SUBSTITUTE(SUBSTITUTE($AU128,IF($AW128="","",$AW128),IF($AW128="","",CONCATENATE("<color=#FFCC71>",$AW128,"</color>"))),IF($AX128="","",$AX128),IF($AX128="","",CONCATENATE("<color=#FFCC71>",$AX128,"</color>"))),IF($AY128="","",$AY128),IF($AY128="","",CONCATENATE("<color=#FFCC71>",$AY128,"</color>"))),IF($AZ128="","",$AZ128),IF($AZ128="","",CONCATENATE("<color=#FFCC71>",$AZ128,"</color>")))) -> 牙尖嘴利，一会儿看我怎么收拾你！ | AU128: 牙尖嘴利，一会儿看我怎么收拾你！
A129: 41014 | B129: 序章 | C129: 1 | D129: 新手序章 | E129: 国内S1 | F129: =VLOOKUP(G129,'#TID_base_up'!B:C,2,0) -> 尤里乌斯 | G129: TID_DialogueConf_41001_name_CN_Main | H129: =VLOOKUP($G129,'#对话模型配置'!$A:$W,MATCH(对话配置表!H$2,'#对话模型配置'!$1:$1,0)) -> altasPath | I129: =VLOOKUP($G129,'#对话模型配置'!$A:$W,MATCH(对话配置表!I$2,'#对话模型配置'!$1:$1,0)) -> picture | J129: TID_DialogueConf_41014_textList_CN_Main | K129: =AT129 -> 别怕，公主殿下！有我尤里乌斯在，他们…… | T129: 1 | U129: 4 | V129: 0 | X129: 3 | Y129: TRUE | Z129: Play_voice_campaign_beginner00_31_bubble_Caesar | AA129: FALSE | AD129: 4.8786669 | AE129: 4.6 | AH129: 0.1 | AL129: 25 | AO129: 1 | AQ129: 0;-60 | AT129: =IF($AU129="","",SUBSTITUTE(SUBSTITUTE(SUBSTITUTE(SUBSTITUTE($AU129,IF($AW129="","",$AW129),IF($AW129="","",CONCATENATE("<color=#FFCC71>",$AW129,"</color>"))),IF($AX129="","",$AX129),IF($AX129="","",CONCATENATE("<color=#FFCC71>",$AX129,"</color>"))),IF($AY129="","",$AY129),IF($AY129="","",CONCATENATE("<color=#FFCC71>",$AY129,"</color>"))),IF($AZ129="","",$AZ129),IF($AZ129="","",CONCATENATE("<color=#FFCC71>",$AZ129,"</color>")))) -> 别怕，公主殿下！有我尤里乌斯在，他们…… | AU129: 别怕，公主殿下！有我尤里乌斯在，他们……
A130: 41015 | B130: 序章 | C130: 1 | D130: 新手序章 | E130: 国内S1 | F130: =VLOOKUP(G130,'#TID_base_up'!B:C,2,0) -> 安德莉娅 | G130: TID_DialogueConf_2055001_name_CN_Main | H130: =VLOOKUP($G130,'#对话模型配置'!$A:$W,MATCH(对话配置表!H$2,'#对话模型配置'!$1:$1,0)) -> altasPath | I130: =VLOOKUP($G130,'#对话模型配置'!$A:$W,MATCH(对话配置表!I$2,'#对话模型配置'!$1:$1,0)) -> picture | J130: TID_DialogueConf_41015_textList_CN_Main | K130: =AT130 -> 知道了，别客套了！有时间站着，不如过来搭把手！ | T130: 1 | U130: 4 | V130: 0 | X130: 3 | Y130: TRUE | Z130: Play_voice_campaign_beginner00_32_bubble_Andrea | AA130: FALSE | AD130: 4.3586669 | AE130: 5.36 | AH130: 0.1 | AL130: 25 | AO130: 17 | AQ130: -110;-100 | AT130: =IF($AU130="","",SUBSTITUTE(SUBSTITUTE(SUBSTITUTE(SUBSTITUTE($AU130,IF($AW130="","",$AW130),IF($AW130="","",CONCATENATE("<color=#FFCC71>",$AW130,"</color>"))),IF($AX130="","",$AX130),IF($AX130="","",CONCATENATE("<color=#FFCC71>",$AX130,"</color>"))),IF($AY130="","",$AY130),IF($AY130="","",CONCATENATE("<color=#FFCC71>",$AY130,"</color>"))),IF($AZ130="","",$AZ130),IF($AZ130="","",CONCATENATE("<color=#FFCC71>",$AZ130,"</color>")))) -> 知道了，别客套了！有时间站着，不如过来搭把手！ | AU130: 知道了，别客套了！有时间站着，不如过来搭把手！
A131: 41016 | B131: 序章 | C131: 1 | D131: 新手序章 | E131: 国内S1 | F131: =VLOOKUP(G131,'#TID_base_up'!B:C,2,0) -> 蛮王 | G131: TID_DialogueConf_41016_name_CN_Main | H131: =VLOOKUP($G131,'#对话模型配置'!$A:$W,MATCH(对话配置表!H$2,'#对话模型配置'!$1:$1,0)) -> altasPath | I131: =VLOOKUP($G131,'#对话模型配置'!$A:$W,MATCH(对话配置表!I$2,'#对话模型配置'!$1:$1,0)) -> picture | J131: TID_DialogueConf_41016_textList_CN_Main | K131: =AT131 -> 老东西，别做无谓的挣扎了，乖乖下马束手就擒吧！ | T131: 1 | U131: 4 | V131: 0 | X131: 3 | Y131: TRUE | Z131: Play_voice_campaign_beginner00_33_bubble_Barbarianking | AA131: FALSE | AD131: 5.2155828 | AE131: 6.22 | AH131: 0.1 | AL131: 25 | AO131: 23 | AQ131: 0;-60 | AT131: =IF($AU131="","",SUBSTITUTE(SUBSTITUTE(SUBSTITUTE(SUBSTITUTE($AU131,IF($AW131="","",$AW131),IF($AW131="","",CONCATENATE("<color=#FFCC71>",$AW131,"</color>"))),IF($AX131="","",$AX131),IF($AX131="","",CONCATENATE("<color=#FFCC71>",$AX131,"</color>"))),IF($AY131="","",$AY131),IF($AY131="","",CONCATENATE("<color=#FFCC71>",$AY131,"</color>"))),IF($AZ131="","",$AZ131),IF($AZ131="","",CONCATENATE("<color=#FFCC71>",$AZ131,"</color>")))) -> 老东西，别做无谓的挣扎了，乖乖下马束手就擒吧！ | AU131: 老东西，别做无谓的挣扎了，乖乖下马束手就擒吧！
A132: 41017 | B132: 序章 | C132: 1 | D132: 新手序章 | E132: 国内S1 | F132: =VLOOKUP(G132,'#TID_base_up'!B:C,2,0) -> 皇帝 | G132: TID_DialogueConf_41017_name_CN_Main | H132: =VLOOKUP($G132,'#对话模型配置'!$A:$W,MATCH(对话配置表!H$2,'#对话模型配置'!$1:$1,0)) -> altasPath | I132: =VLOOKUP($G132,'#对话模型配置'!$A:$W,MATCH(对话配置表!I$2,'#对话模型配置'!$1:$1,0)) -> picture | J132: TID_DialogueConf_41017_textList_CN_Main | K132: =AT132 -> 化外蛮夷，今天就让我来教教你，什么是基本礼仪！ | T132: 1 | U132: 4 | V132: 0 | X132: 3 | Y132: TRUE | Z132: Play_voice_campaign_beginner00_34_bubble_King | AA132: FALSE | AD132: 6.0304999 | AE132: 7.03 | AH132: 0.1 | AL132: 25 | AO132: 32 | AQ132: -90;-60 | AT132: =IF($AU132="","",SUBSTITUTE(SUBSTITUTE(SUBSTITUTE(SUBSTITUTE($AU132,IF($AW132="","",$AW132),IF($AW132="","",CONCATENATE("<color=#FFCC71>",$AW132,"</color>"))),IF($AX132="","",$AX132),IF($AX132="","",CONCATENATE("<color=#FFCC71>",$AX132,"</color>"))),IF($AY132="","",$AY132),IF($AY132="","",CONCATENATE("<color=#FFCC71>",$AY132,"</color>"))),IF($AZ132="","",$AZ132),IF($AZ132="","",CONCATENATE("<color=#FFCC71>",$AZ132,"</color>")))) -> 化外蛮夷，今天就让我来教教你，什么是基本礼仪！ | AU132: 化外蛮夷，今天就让我来教教你，什么是基本礼仪！
A133: 41018 | B133: 序章 | C133: 1 | D133: 新手序章 | E133: 国内S1 | F133: =VLOOKUP(G133,'#TID_base_up'!B:C,2,0) -> 尤里乌斯 | G133: TID_DialogueConf_41001_name_CN_Main | H133: =VLOOKUP($G133,'#对话模型配置'!$A:$W,MATCH(对话配置表!H$2,'#对话模型配置'!$1:$1,0)) -> altasPath | I133: =VLOOKUP($G133,'#对话模型配置'!$A:$W,MATCH(对话配置表!I$2,'#对话模型配置'!$1:$1,0)) -> picture | J133: TID_DialogueConf_41018_textList_CN_Main | T133: 1 | U133: 4 | V133: 0 | X133: 3 | AA133: FALSE | AD133: 4 | AE133: 5 | AH133: 0.1 | AL133: 25 | AT133: =IF($AU133="","",SUBSTITUTE(SUBSTITUTE(SUBSTITUTE(SUBSTITUTE($AU133,IF($AW133="","",$AW133),IF($AW133="","",CONCATENATE("<color=#FFCC71>",$AW133,"</color>"))),IF($AX133="","",$AX133),IF($AX133="","",CONCATENATE("<color=#FFCC71>",$AX133,"</color>"))),IF($AY133="","",$AY133),IF($AY133="","",CONCATENATE("<color=#FFCC71>",$AY133,"</color>"))),IF($AZ133="","",$AZ133),IF($AZ133="","",CONCATENATE("<color=#FFCC71>",$AZ133,"</color>")))) -> 陛下！ | AU133: 陛下！
A134: 41019 | B134: 序章 | C134: 1 | D134: 新手序章 | E134: 国内S1 | F134: =VLOOKUP(G134,'#TID_base_up'!B:C,2,0) -> 皇帝 | G134: TID_DialogueConf_41017_name_CN_Main | H134: =VLOOKUP($G134,'#对话模型配置'!$A:$W,MATCH(对话配置表!H$2,'#对话模型配置'!$1:$1,0)) -> altasPath | I134: =VLOOKUP($G134,'#对话模型配置'!$A:$W,MATCH(对话配置表!I$2,'#对话模型配置'!$1:$1,0)) -> picture | J134: TID_DialogueConf_41019_textList_CN_Main | K134: =AT134 -> 想不到，最后竟然只有你来陪我打这一场仗！ | T134: 1 | U134: 4 | V134: 0 | X134: 3 | Y134: TRUE | Z134: Play_voice_campaign_beginner00_38_bubble_King | AA134: FALSE | AD134: 4.4648328 | AE134: 5.46 | AH134: 0.1 | AL134: 25 | AO134: 32 | AQ134: -90;-95 | AT134: =IF($AU134="","",SUBSTITUTE(SUBSTITUTE(SUBSTITUTE(SUBSTITUTE($AU134,IF($AW134="","",$AW134),IF($AW134="","",CONCATENATE("<color=#FFCC71>",$AW134,"</color>"))),IF($AX134="","",$AX134),IF($AX134="","",CONCATENATE("<color=#FFCC71>",$AX134,"</color>"))),IF($AY134="","",$AY134),IF($AY134="","",CONCATENATE("<color=#FFCC71>",$AY134,"</color>"))),IF($AZ134="","",$AZ134),IF($AZ134="","",CONCATENATE("<color=#FFCC71>",$AZ134,"</color>")))) -> 想不到，最后竟然只有你来陪我打这一场仗！ | AU134: 想不到，最后竟然只有你来陪我打这一场仗！
A135: 41020 | B135: 序章 | C135: 1 | D135: 新手序章 | E135: 国内S1 | F135: =VLOOKUP(G135,'#TID_base_up'!B:C,2,0) -> 蛮王 | G135: TID_DialogueConf_41016_name_CN_Main | H135: =VLOOKUP($G135,'#对话模型配置'!$A:$W,MATCH(对话配置表!H$2,'#对话模型配置'!$1:$1,0)) -> altasPath | I135: =VLOOKUP($G135,'#对话模型配置'!$A:$W,MATCH(对话配置表!I$2,'#对话模型配置'!$1:$1,0)) -> picture | J135: TID_DialogueConf_41020_textList_CN_Main | K135: =AT135 -> 可笑，逃跑的见过无数，赶来送人头的倒是第一回见！ | T135: 1 | U135: 4 | V135: 0 | X135: 3 | Y135: TRUE | Z135: Play_voice_campaign_beginner00_39_bubble_Barbarianking | AA135: FALSE | AD135: 6.0549998 | AE135: 7.05 | AH135: 0.1 | AL135: 25 | AO135: 23 | AQ135: -90;-15 | AT135: =IF($AU135="","",SUBSTITUTE(SUBSTITUTE(SUBSTITUTE(SUBSTITUTE($AU135,IF($AW135="","",$AW135),IF($AW135="","",CONCATENATE("<color=#FFCC71>",$AW135,"</color>"))),IF($AX135="","",$AX135),IF($AX135="","",CONCATENATE("<color=#FFCC71>",$AX135,"</color>"))),IF($AY135="","",$AY135),IF($AY135="","",CONCATENATE("<color=#FFCC71>",$AY135,"</color>"))),IF($AZ135="","",$AZ135),IF($AZ135="","",CONCATENATE("<color=#FFCC71>",$AZ135,"</color>")))) -> 可笑，逃跑的见过无数，赶来送人头的倒是第一回见！ | AU135: 可笑，逃跑的见过无数，赶来送人头的倒是第一回见！
A136: 41021 | B136: 序章 | C136: 1 | D136: 新手序章 | E136: 国内S1 | F136: =VLOOKUP(G136,'#TID_base_up'!B:C,2,0) -> 蛮王 | G136: TID_DialogueConf_41016_name_CN_Main | H136: =VLOOKUP($G136,'#对话模型配置'!$A:$W,MATCH(对话配置表!H$2,'#对话模型配置'!$1:$1,0)) -> altasPath | I136: =VLOOKUP($G136,'#对话模型配置'!$A:$W,MATCH(对话配置表!I$2,'#对话模型配置'!$1:$1,0)) -> picture | J136: TID_DialogueConf_41021_textList_CN_Main | K136: =AT136 -> 哼，这老东西就算给你们又如何！ | T136: 1 | U136: 4 | V136: 0 | X136: 3 | Y136: TRUE | Z136: Play_voice_campaign_beginner00_43_bubble_Barbarianking | AA136: FALSE | AD136: 3.0298331 | AE136: 4.03 | AH136: 0.1 | AL136: 25 | AO136: 23 | AT136: =IF($AU136="","",SUBSTITUTE(SUBSTITUTE(SUBSTITUTE(SUBSTITUTE($AU136,IF($AW136="","",$AW136),IF($AW136="","",CONCATENATE("<color=#FFCC71>",$AW136,"</color>"))),IF($AX136="","",$AX136),IF($AX136="","",CONCATENATE("<color=#FFCC71>",$AX136,"</color>"))),IF($AY136="","",$AY136),IF($AY136="","",CONCATENATE("<color=#FFCC71>",$AY136,"</color>"))),IF($AZ136="","",$AZ136),IF($AZ136="","",CONCATENATE("<color=#FFCC71>",$AZ136,"</color>")))) -> 哼，这老东西就算给你们又如何！ | AU136: 哼，这老东西就算给你们又如何！
A137: 41022 | B137: 序章 | C137: 1 | D137: 新手序章 | E137: 国内S1 | F137: =VLOOKUP(G137,'#TID_base_up'!B:C,2,0) -> 安德莉娅 | G137: TID_DialogueConf_2055001_name_CN_Main | H137: =VLOOKUP($G137,'#对话模型配置'!$A:$W,MATCH(对话配置表!H$2,'#对话模型配置'!$1:$1,0)) -> altasPath | I137: =VLOOKUP($G137,'#对话模型配置'!$A:$W,MATCH(对话配置表!I$2,'#对话模型配置'!$1:$1,0)) -> picture | J137: TID_DialogueConf_41022_textList_CN_Main | K137: =AT137 -> 糟糕糟糕！蛮族又冲过来了！快掩护陛下撤退！ | T137: 1 | U137: 4 | V137: 0 | X137: 3 | Y137: TRUE | Z137: Play_voice_campaign_beginner00_44_bubble_Andrea | AA137: FALSE | AD137: 4.1626668 | AE137: 5.16 | AH137: 0.1 | AL137: 25 | AO137: 17 | AQ137: 0;-100 | AT137: =IF($AU137="","",SUBSTITUTE(SUBSTITUTE(SUBSTITUTE(SUBSTITUTE($AU137,IF($AW137="","",$AW137),IF($AW137="","",CONCATENATE("<color=#FFCC71>",$AW137,"</color>"))),IF($AX137="","",$AX137),IF($AX137="","",CONCATENATE("<color=#FFCC71>",$AX137,"</color>"))),IF($AY137="","",$AY137),IF($AY137="","",CONCATENATE("<color=#FFCC71>",$AY137,"</color>"))),IF($AZ137="","",$AZ137),IF($AZ137="","",CONCATENATE("<color=#FFCC71>",$AZ137,"</color>")))) -> 糟糕糟糕！蛮族又冲过来了！快掩护陛下撤退！ | AU137: 糟糕糟糕！蛮族又冲过来了！快掩护陛下撤退！
A138: 41023 | B138: 序章 | C138: 1 | D138: 新手序章 | E138: 国内S1 | F138: =VLOOKUP(G138,'#TID_base_up'!B:C,2,0) -> 皇帝 | G138: TID_DialogueConf_41017_name_CN_Main | H138: =VLOOKUP($G138,'#对话模型配置'!$A:$W,MATCH(对话配置表!H$2,'#对话模型配置'!$1:$1,0)) -> altasPath | I138: =VLOOKUP($G138,'#对话模型配置'!$A:$W,MATCH(对话配置表!I$2,'#对话模型配置'!$1:$1,0)) -> picture | J138: TID_DialogueConf_41023_textList_CN_Main | K138: =AT138 -> 也许，这就是<color=#FFCC71>命运的安排</color>吧……<color=#FFCC71>帝国</color>的未来就<color=#FFCC71>交给你了</color>！ | T138: 1 | U138: 1 | V138: 2 | X138: 3 | Y138: FALSE | AA138: FALSE | AD138: 6.0888329 | AE138: 7.09 | AH138: 1.5 | AL138: 25 | AM138: assets/bundleresources/characters/a/hero/p_ah_cstt_facial.prefab | AN138: chapter_2_13 | AT138: =IF($AU138="","",SUBSTITUTE(SUBSTITUTE(SUBSTITUTE(SUBSTITUTE($AU138,IF($AW138="","",$AW138),IF($AW138="","",CONCATENATE("<color=#FFCC71>",$AW138,"</color>"))),IF($AX138="","",$AX138),IF($AX138="","",CONCATENATE("<color=#FFCC71>",$AX138,"</color>"))),IF($AY138="","",$AY138),IF($AY138="","",CONCATENATE("<color=#FFCC71>",$AY138,"</color>"))),IF($AZ138="","",$AZ138),IF($AZ138="","",CONCATENATE("<color=#FFCC71>",$AZ138,"</color>")))) -> 也许，这就是<color=#FFCC71>命运的安排</color>吧……<color=#FFCC71>帝国</color>的未来就<color=#FFCC71>交给你了</color>！ | AU138: 也许，这就是命运的安排吧……帝国的未来就交给你了！ | AW138: 命运的安排 | AX138: 帝国 | AY138: 交给你了
A139: 41023 | B139: 序章 | C139: 2 | D139: 新手序章 | E139: 国内S1 | F139: =VLOOKUP(G139,'#TID_base_up'!B:C,2,0) -> 皇帝 | G139: TID_DialogueConf_41017_name_CN_Main | H139: =VLOOKUP($G139,'#对话模型配置'!$A:$W,MATCH(对话配置表!H$2,'#对话模型配置'!$1:$1,0)) -> altasPath | I139: =VLOOKUP($G139,'#对话模型配置'!$A:$W,MATCH(对话配置表!I$2,'#对话模型配置'!$1:$1,0)) -> picture | J139: TID_DialogueConf_41023_textList_140333048854_CN_Main | K139: =AT139 -> 你们一定要<color=#FFCC71>活下去</color>，只要你们活着，<color=#FFCC71>帝国</color>就一定<color=#FFCC71>不会灭亡</color>！ | T139: 1 | U139: 1 | V139: 2 | X139: 3 | Y139: FALSE | AA139: FALSE | AD139: 8.5306664 | AE139: 9.53 | AH139: 1.5 | AL139: 25 | AM139: assets/bundleresources/characters/a/hero/p_ah_cstt_facial.prefab | AN139: chapter_2_14 | AT139: =IF($AU139="","",SUBSTITUTE(SUBSTITUTE(SUBSTITUTE(SUBSTITUTE($AU139,IF($AW139="","",$AW139),IF($AW139="","",CONCATENATE("<color=#FFCC71>",$AW139,"</color>"))),IF($AX139="","",$AX139),IF($AX139="","",CONCATENATE("<color=#FFCC71>",$AX139,"</color>"))),IF($AY139="","",$AY139),IF($AY139="","",CONCATENATE("<color=#FFCC71>",$AY139,"</color>"))),IF($AZ139="","",$AZ139),IF($AZ139="","",CONCATENATE("<color=#FFCC71>",$AZ139,"</color>")))) -> 你们一定要<color=#FFCC71>活下去</color>，只要你们活着，<color=#FFCC71>帝国</color>就一定<color=#FFCC71>不会灭亡</color>！ | AU139: 你们一定要活下去，只要你们活着，帝国就一定不会灭亡！ | AW139: 活下去 | AX139: 帝国 | AY139: 不会灭亡
A140: 41024 | B140: 序章 | C140: 1 | D140: 新手序章 | E140: 国内S1 | F140: =VLOOKUP(G140,'#TID_base_up'!B:C,2,0) -> 蛮族杂鱼 | G140: TID_DialogueConf_41024_name_CN_Main | H140: =VLOOKUP($G140,'#对话模型配置'!$A:$W,MATCH(对话配置表!H$2,'#对话模型配置'!$1:$1,0)) -> altasPath | I140: =VLOOKUP($G140,'#对话模型配置'!$A:$W,MATCH(对话配置表!I$2,'#对话模型配置'!$1:$1,0)) -> picture | J140: TID_DialogueConf_41024_textList_CN_Main | K140: =AT140 -> 眼睛都给我瞪大点儿！哪怕一只苍蝇都不能放过！ | T140: 1 | U140: 3 | V140: 0 | X140: 3 | Y140: TRUE | Z140: Play_voice_campaign_beginner00_05_bubble_Barbarian | AA140: FALSE | AD140: 3.8036251 | AE140: 4.8 | AH140: 0.1 | AL140: 25 | AT140: =IF($AU140="","",SUBSTITUTE(SUBSTITUTE(SUBSTITUTE(SUBSTITUTE($AU140,IF($AW140="","",$AW140),IF($AW140="","",CONCATENATE("<color=#FFCC71>",$AW140,"</color>"))),IF($AX140="","",$AX140),IF($AX140="","",CONCATENATE("<color=#FFCC71>",$AX140,"</color>"))),IF($AY140="","",$AY140),IF($AY140="","",CONCATENATE("<color=#FFCC71>",$AY140,"</color>"))),IF($AZ140="","",$AZ140),IF($AZ140="","",CONCATENATE("<color=#FFCC71>",$AZ140,"</color>")))) -> 眼睛都给我瞪大点儿！哪怕一只苍蝇都不能放过！ | AU140: 眼睛都给我瞪大点儿！哪怕一只苍蝇都不能放过！
A141: 41025 | B141: 序章 | C141: 1 | D141: 新手序章 | E141: 国内S1 | F141: =VLOOKUP(G141,'#TID_base_up'!B:C,2,0) -> 尤里乌斯 | G141: TID_DialogueConf_41001_name_CN_Main | H141: =VLOOKUP($G141,'#对话模型配置'!$A:$W,MATCH(对话配置表!H$2,'#对话模型配置'!$1:$1,0)) -> altasPath | I141: =VLOOKUP($G141,'#对话模型配置'!$A:$W,MATCH(对话配置表!I$2,'#对话模型配置'!$1:$1,0)) -> picture | J141: TID_DialogueConf_41025_textList_CN_Main | K141: =AT141 -> 让我来，利剑胜长枪，再多枪兵都是我剑下炮灰！ | T141: 1 | U141: 4 | V141: 0 | X141: 3 | Y141: TRUE | Z141: Play_voice_campaign_beginner00_42_bubble_Caesar | AA141: FALSE | AD141: 6.3699999 | AE141: 7.37 | AH141: 0.1 | AL141: 25 | AO141: 1 | AT141: =IF($AU141="","",SUBSTITUTE(SUBSTITUTE(SUBSTITUTE(SUBSTITUTE($AU141,IF($AW141="","",$AW141),IF($AW141="","",CONCATENATE("<color=#FFCC71>",$AW141,"</color>"))),IF($AX141="","",$AX141),IF($AX141="","",CONCATENATE("<color=#FFCC71>",$AX141,"</color>"))),IF($AY141="","",$AY141),IF($AY141="","",CONCATENATE("<color=#FFCC71>",$AY141,"</color>"))),IF($AZ141="","",$AZ141),IF($AZ141="","",CONCATENATE("<color=#FFCC71>",$AZ141,"</color>")))) -> 让我来，利剑胜长枪，再多枪兵都是我剑下炮灰！ | AU141: 让我来，利剑胜长枪，再多枪兵都是我剑下炮灰！
A142: 41026 | B142: 序章 | C142: 1 | D142: 新手序章 | E142: 国内S1 | F142: =VLOOKUP(G142,'#TID_base_up'!B:C,2,0) -> 安德莉娅 | G142: TID_DialogueConf_2055001_name_CN_Main | H142: =VLOOKUP($G142,'#对话模型配置'!$A:$W,MATCH(对话配置表!H$2,'#对话模型配置'!$1:$1,0)) -> altasPath | I142: =VLOOKUP($G142,'#对话模型配置'!$A:$W,MATCH(对话配置表!I$2,'#对话模型配置'!$1:$1,0)) -> picture | J142: TID_DialogueConf_41026_textList_CN_Main | K142: =AT142 -> 蛮王又准备施放技能了，快打断他！ | T142: 1 | U142: 4 | V142: 0 | X142: 3 | Y142: FALSE | Z142: Play_voice_campaign_beginner00_41_tips_Andrea | AA142: FALSE | AD142: 3.0566671 | AE142: 4.06 | AH142: 0.1 | AL142: 25 | AO142: 17 | AT142: =IF($AU142="","",SUBSTITUTE(SUBSTITUTE(SUBSTITUTE(SUBSTITUTE($AU142,IF($AW142="","",$AW142),IF($AW142="","",CONCATENATE("<color=#FFCC71>",$AW142,"</color>"))),IF($AX142="","",$AX142),IF($AX142="","",CONCATENATE("<color=#FFCC71>",$AX142,"</color>"))),IF($AY142="","",$AY142),IF($AY142="","",CONCATENATE("<color=#FFCC71>",$AY142,"</color>"))),IF($AZ142="","",$AZ142),IF($AZ142="","",CONCATENATE("<color=#FFCC71>",$AZ142,"</color>")))) -> 蛮王又准备施放技能了，快打断他！ | AU142: 蛮王又准备施放技能了，快打断他！
A143: 41027 | B143: 序章 | C143: 1 | D143: 新手序章 | E143: 国内S1 | F143: =VLOOKUP(G143,'#TID_base_up'!B:C,2,0) -> 尤里乌斯 | G143: TID_DialogueConf_41001_name_CN_Main | H143: =VLOOKUP($G143,'#对话模型配置'!$A:$W,MATCH(对话配置表!H$2,'#对话模型配置'!$1:$1,0)) -> altasPath | I143: =VLOOKUP($G143,'#对话模型配置'!$A:$W,MATCH(对话配置表!I$2,'#对话模型配置'!$1:$1,0)) -> picture | J143: TID_DialogueConf_41027_textList_CN_Main | K143: =AT143 -> 你的命令，就是我的使命，列队出发！ | T143: 1 | U143: 4 | V143: 0 | X143: 3 | Y143: TRUE | Z143: Play_voice_campaign_beginner00_08_bubble_Caesar | AA143: FALSE | AD143: 3.557333 | AE143: 4.56 | AH143: 0.1 | AL143: 25 | AO143: 1 | AT143: =IF($AU143="","",SUBSTITUTE(SUBSTITUTE(SUBSTITUTE(SUBSTITUTE($AU143,IF($AW143="","",$AW143),IF($AW143="","",CONCATENATE("<color=#FFCC71>",$AW143,"</color>"))),IF($AX143="","",$AX143),IF($AX143="","",CONCATENATE("<color=#FFCC71>",$AX143,"</color>"))),IF($AY143="","",$AY143),IF($AY143="","",CONCATENATE("<color=#FFCC71>",$AY143,"</color>"))),IF($AZ143="","",$AZ143),IF($AZ143="","",CONCATENATE("<color=#FFCC71>",$AZ143,"</color>")))) -> 你的命令，就是我的使命，列队出发！ | AU143: 你的命令，就是我的使命，列队出发！
A144: 41028 | B144: 序章 | C144: 1 | D144: 新手序章 | E144: 国内S1 | F144: =VLOOKUP(G144,'#TID_base_up'!B:C,2,0) -> 尤里乌斯 | G144: TID_DialogueConf_41001_name_CN_Main | H144: =VLOOKUP($G144,'#对话模型配置'!$A:$W,MATCH(对话配置表!H$2,'#对话模型配置'!$1:$1,0)) -> altasPath | I144: =VLOOKUP($G144,'#对话模型配置'!$A:$W,MATCH(对话配置表!I$2,'#对话模型配置'!$1:$1,0)) -> picture | J144: TID_DialogueConf_41028_textList_CN_Main | K144: =AT144 -> 士兵们，低调点，别让敌人发现了。 | T144: 1 | U144: 4 | V144: 0 | X144: 3 | Y144: TRUE | Z144: Play_voice_campaign_beginner00_15_bubble_Caesar | AA144: FALSE | AD144: 3.2906671 | AE144: 4.29 | AH144: 0.1 | AL144: 25 | AO144: 1 | AT144: =IF($AU144="","",SUBSTITUTE(SUBSTITUTE(SUBSTITUTE(SUBSTITUTE($AU144,IF($AW144="","",$AW144),IF($AW144="","",CONCATENATE("<color=#FFCC71>",$AW144,"</color>"))),IF($AX144="","",$AX144),IF($AX144="","",CONCATENATE("<color=#FFCC71>",$AX144,"</color>"))),IF($AY144="","",$AY144),IF($AY144="","",CONCATENATE("<color=#FFCC71>",$AY144,"</color>"))),IF($AZ144="","",$AZ144),IF($AZ144="","",CONCATENATE("<color=#FFCC71>",$AZ144,"</color>")))) -> 士兵们，低调点，别让敌人发现了。 | AU144: 士兵们，低调点，别让敌人发现了。
A145: 41029 | B145: 序章 | C145: 1 | D145: 新手序章 | E145: 国内S1 | F145: =VLOOKUP(G145,'#TID_base_up'!B:C,2,0) -> 尤里乌斯 | G145: TID_DialogueConf_41001_name_CN_Main | H145: =VLOOKUP($G145,'#对话模型配置'!$A:$W,MATCH(对话配置表!H$2,'#对话模型配置'!$1:$1,0)) -> altasPath | I145: =VLOOKUP($G145,'#对话模型配置'!$A:$W,MATCH(对话配置表!I$2,'#对话模型配置'!$1:$1,0)) -> picture | J145: TID_DialogueConf_41029_textList_CN_Main | K145: =AT145 -> 列队出征，击溃敌人！ | T145: 1 | U145: 4 | V145: 0 | X145: 3 | Y145: TRUE | AA145: FALSE | AD145: 3.557333 | AE145: 4.56 | AH145: 0.1 | AL145: 25 | AO145: 1 | AT145: =IF($AU145="","",SUBSTITUTE(SUBSTITUTE(SUBSTITUTE(SUBSTITUTE($AU145,IF($AW145="","",$AW145),IF($AW145="","",CONCATENATE("<color=#FFCC71>",$AW145,"</color>"))),IF($AX145="","",$AX145),IF($AX145="","",CONCATENATE("<color=#FFCC71>",$AX145,"</color>"))),IF($AY145="","",$AY145),IF($AY145="","",CONCATENATE("<color=#FFCC71>",$AY145,"</color>"))),IF($AZ145="","",$AZ145),IF($AZ145="","",CONCATENATE("<color=#FFCC71>",$AZ145,"</color>")))) -> 列队出征，击溃敌人！ | AU145: 列队出征，击溃敌人！
A146: 41030 | B146: 序章 | C146: 1 | D146: 新手序章 | E146: 国内S1 | F146: =VLOOKUP(G146,'#TID_base_up'!B:C,2,0) -> 尤里乌斯 | G146: TID_DialogueConf_41001_name_CN_Main | H146: =VLOOKUP($G146,'#对话模型配置'!$A:$W,MATCH(对话配置表!H$2,'#对话模型配置'!$1:$1,0)) -> altasPath | I146: =VLOOKUP($G146,'#对话模型配置'!$A:$W,MATCH(对话配置表!I$2,'#对话模型配置'!$1:$1,0)) -> picture | J146: TID_DialogueConf_41030_textList_CN_Main | K146: =AT146 -> 剑士克制枪兵！我们有兵种优势！随我冲散他们！ | T146: 1 | U146: 4 | V146: 0 | X146: 3 | Y146: TRUE | Z146: Play_voice_campaign_beginner00_30_bubble_Caesar | AA146: FALSE | AD146: 5.212667 | AE146: 6.21 | AH146: 0.1 | AL146: 25 | AO146: 1 | AT146: =IF($AU146="","",SUBSTITUTE(SUBSTITUTE(SUBSTITUTE(SUBSTITUTE($AU146,IF($AW146="","",$AW146),IF($AW146="","",CONCATENATE("<color=#FFCC71>",$AW146,"</color>"))),IF($AX146="","",$AX146),IF($AX146="","",CONCATENATE("<color=#FFCC71>",$AX146,"</color>"))),IF($AY146="","",$AY146),IF($AY146="","",CONCATENATE("<color=#FFCC71>",$AY146,"</color>"))),IF($AZ146="","",$AZ146),IF($AZ146="","",CONCATENATE("<color=#FFCC71>",$AZ146,"</color>")))) -> 剑士克制枪兵！我们有兵种优势！随我冲散他们！ | AU146: 剑士克制枪兵！我们有兵种优势！随我冲散他们！
A147: 41031 | B147: 序章 | C147: 1 | D147: 新手序章 | E147: 国内S1 | F147: =VLOOKUP(G147,'#TID_base_up'!B:C,2,0) -> 尤里乌斯 | G147: TID_DialogueConf_41001_name_CN_Main | H147: =VLOOKUP($G147,'#对话模型配置'!$A:$W,MATCH(对话配置表!H$2,'#对话模型配置'!$1:$1,0)) -> altasPath | I147: =VLOOKUP($G147,'#对话模型配置'!$A:$W,MATCH(对话配置表!I$2,'#对话模型配置'!$1:$1,0)) -> picture | J147: TID_DialogueConf_41031_textList_CN_Main | K147: =AT147 -> 听我号令，全军出击，碾碎他们！ | T147: 1 | U147: 4 | V147: 0 | X147: 3 | Y147: TRUE | Z147: Play_voice_campaign_beginner00_37_bubble_Caesar | AA147: FALSE | AD147: 3.904 | AE147: 4.9 | AH147: 0.1 | AL147: 25 | AO147: 1 | AT147: =IF($AU147="","",SUBSTITUTE(SUBSTITUTE(SUBSTITUTE(SUBSTITUTE($AU147,IF($AW147="","",$AW147),IF($AW147="","",CONCATENATE("<color=#FFCC71>",$AW147,"</color>"))),IF($AX147="","",$AX147),IF($AX147="","",CONCATENATE("<color=#FFCC71>",$AX147,"</color>"))),IF($AY147="","",$AY147),IF($AY147="","",CONCATENATE("<color=#FFCC71>",$AY147,"</color>"))),IF($AZ147="","",$AZ147),IF($AZ147="","",CONCATENATE("<color=#FFCC71>",$AZ147,"</color>")))) -> 听我号令，全军出击，碾碎他们！ | AU147: 听我号令，全军出击，碾碎他们！
A148: 41032 | B148: 序章 | C148: 1 | D148: 新手序章 | E148: 国内S1 | F148: =VLOOKUP(G148,'#TID_base_up'!B:C,2,0) -> 皇帝 | G148: TID_DialogueConf_41017_name_CN_Main | H148: =VLOOKUP($G148,'#对话模型配置'!$A:$W,MATCH(对话配置表!H$2,'#对话模型配置'!$1:$1,0)) -> altasPath | I148: =VLOOKUP($G148,'#对话模型配置'!$A:$W,MATCH(对话配置表!I$2,'#对话模型配置'!$1:$1,0)) -> picture | J148: TID_DialogueConf_41032_textList_CN_Main | K148: =AT148 -> 帝国将士们…我以皇帝之名下令…撤离战场！ | T148: 1 | U148: 4 | V148: 0 | X148: 3 | Y148: TRUE | Z148: Play_voice_campaign_beginner00_45_bubble_King | AA148: FALSE | AD148: 6.0888329 | AE148: 7.09 | AH148: 0.1 | AL148: 25 | AO148: 32 | AT148: =IF($AU148="","",SUBSTITUTE(SUBSTITUTE(SUBSTITUTE(SUBSTITUTE($AU148,IF($AW148="","",$AW148),IF($AW148="","",CONCATENATE("<color=#FFCC71>",$AW148,"</color>"))),IF($AX148="","",$AX148),IF($AX148="","",CONCATENATE("<color=#FFCC71>",$AX148,"</color>"))),IF($AY148="","",$AY148),IF($AY148="","",CONCATENATE("<color=#FFCC71>",$AY148,"</color>"))),IF($AZ148="","",$AZ148),IF($AZ148="","",CONCATENATE("<color=#FFCC71>",$AZ148,"</color>")))) -> 帝国将士们…我以皇帝之名下令…撤离战场！ | AU148: 帝国将士们…我以皇帝之名下令…撤离战场！
A149: 41033 | B149: 序章 | C149: 1 | D149: 新手序章 | E149: 国内S1 | F149: =VLOOKUP(G149,'#TID_base_up'!B:C,2,0) -> 安德莉娅 | G149: TID_DialogueConf_2055001_name_CN_Main | H149: =VLOOKUP($G149,'#对话模型配置'!$A:$W,MATCH(对话配置表!H$2,'#对话模型配置'!$1:$1,0)) -> altasPath | I149: =VLOOKUP($G149,'#对话模型配置'!$A:$W,MATCH(对话配置表!I$2,'#对话模型配置'!$1:$1,0)) -> picture | J149: TID_DialogueConf_41033_textList_CN_Main | K149: =AT149 -> 领主大人，擒贼先擒王，快<color=#FFCC71>集合队伍</color>全力进攻敌人头目！ | T149: 1 | U149: 1 | V149: 0 | X149: 3 | Y149: TRUE | Z149: Play_voice_campaign_beginner00_35_02_Andrea | AA149: FALSE | AC149: 20001012 | AD149: 6.0386672 | AE149: 7.04 | AH149: 0.1 | AL149: 25 | AM149: =VLOOKUP($F149,'#对话模型配置'!$A:$W,MATCH(对话配置表!AM$2,'#对话模型配置'!$1:$1,0),FALSE) -> 30001001 | AN149: chapter_0_6 | AT149: =IF($AU149="","",SUBSTITUTE(SUBSTITUTE(SUBSTITUTE(SUBSTITUTE($AU149,IF($AW149="","",$AW149),IF($AW149="","",CONCATENATE("<color=#FFCC71>",$AW149,"</color>"))),IF($AX149="","",$AX149),IF($AX149="","",CONCATENATE("<color=#FFCC71>",$AX149,"</color>"))),IF($AY149="","",$AY149),IF($AY149="","",CONCATENATE("<color=#FFCC71>",$AY149,"</color>"))),IF($AZ149="","",$AZ149),IF($AZ149="","",CONCATENATE("<color=#FFCC71>",$AZ149,"</color>")))) -> 领主大人，擒贼先擒王，快<color=#FFCC71>集合队伍</color>全力进攻敌人头目！ | AU149: 领主大人，擒贼先擒王，快集合队伍全力进攻敌人头目！ | AW149: 集合队伍
A150: 41034 | B150: 序章 | C150: 1 | D150: 新手序章 | E150: 国内S1 | F150: =VLOOKUP(G150,'#TID_base_up'!B:C,2,0) -> 尤里乌斯 | G150: TID_DialogueConf_41001_name_CN_Main | H150: =VLOOKUP($G150,'#对话模型配置'!$A:$W,MATCH(对话配置表!H$2,'#对话模型配置'!$1:$1,0)) -> altasPath | I150: =VLOOKUP($G150,'#对话模型配置'!$A:$W,MATCH(对话配置表!I$2,'#对话模型配置'!$1:$1,0)) -> picture | J150: TID_DialogueConf_41034_textList_CN_Main | K150: =AT150 -> 守住阵线！只要我们在，帝国一定可以翻盘！ | T150: 1 | U150: 4 | V150: 0 | X150: 3 | Y150: TRUE | Z150: Play_voice_campaign_beginner00_46_02_bubble_Caesar | AA150: FALSE | AD150: 4.9046669 | AE150: 5.9 | AH150: 0.1 | AL150: 25 | AO150: 1 | AT150: =IF($AU150="","",SUBSTITUTE(SUBSTITUTE(SUBSTITUTE(SUBSTITUTE($AU150,IF($AW150="","",$AW150),IF($AW150="","",CONCATENATE("<color=#FFCC71>",$AW150,"</color>"))),IF($AX150="","",$AX150),IF($AX150="","",CONCATENATE("<color=#FFCC71>",$AX150,"</color>"))),IF($AY150="","",$AY150),IF($AY150="","",CONCATENATE("<color=#FFCC71>",$AY150,"</color>"))),IF($AZ150="","",$AZ150),IF($AZ150="","",CONCATENATE("<color=#FFCC71>",$AZ150,"</color>")))) -> 守住阵线！只要我们在，帝国一定可以翻盘！ | AU150: 守住阵线！只要我们在，帝国一定可以翻盘！
A151: 41035 | B151: 序章 | C151: 1 | D151: 新手序章 | E151: 国内S1 | F151: =VLOOKUP(G151,'#TID_base_up'!B:C,2,0) -> 安德莉娅 | G151: TID_DialogueConf_2055001_name_CN_Main | H151: =VLOOKUP($G151,'#对话模型配置'!$A:$W,MATCH(对话配置表!H$2,'#对话模型配置'!$1:$1,0)) -> altasPath | I151: =VLOOKUP($G151,'#对话模型配置'!$A:$W,MATCH(对话配置表!I$2,'#对话模型配置'!$1:$1,0)) -> picture | J151: TID_DialogueConf_41026_textList_CN_Main | K151: =AT151 -> 蛮王又准备施放技能了，快打断他！ | T151: 1 | U151: 4 | V151: 0 | X151: 3 | Y151: TRUE | Z151: Play_voice_campaign_beginner00_41_tips_Andrea | AA151: TRUE | AD151: 3.0566671 | AE151: 4.06 | AH151: 0.1 | AL151: 25 | AO151: 17 | AT151: =IF($AU151="","",SUBSTITUTE(SUBSTITUTE(SUBSTITUTE(SUBSTITUTE($AU151,IF($AW151="","",$AW151),IF($AW151="","",CONCATENATE("<color=#FFCC71>",$AW151,"</color>"))),IF($AX151="","",$AX151),IF($AX151="","",CONCATENATE("<color=#FFCC71>",$AX151,"</color>"))),IF($AY151="","",$AY151),IF($AY151="","",CONCATENATE("<color=#FFCC71>",$AY151,"</color>"))),IF($AZ151="","",$AZ151),IF($AZ151="","",CONCATENATE("<color=#FFCC71>",$AZ151,"</color>")))) -> 蛮王又准备施放技能了，快打断他！ | AU151: 蛮王又准备施放技能了，快打断他！
A152: 41036 | B152: 序章 | C152: 1 | D152: 新手序章 | E152: 国内S1 | F152: =VLOOKUP(G152,'#TID_base_up'!B:C,2,0) -> 蛮王 | G152: TID_DialogueConf_41016_name_CN_Main | H152: =VLOOKUP($G152,'#对话模型配置'!$A:$W,MATCH(对话配置表!H$2,'#对话模型配置'!$1:$1,0)) -> altasPath | I152: =VLOOKUP($G152,'#对话模型配置'!$A:$W,MATCH(对话配置表!I$2,'#对话模型配置'!$1:$1,0)) -> picture | J152: TID_DialogueConf_41036_textList_CN_Main | K152: =AT152 -> 蛮族大军即将横扫整个帝国，你们无路可逃！ | T152: 1 | U152: 4 | V152: 0 | X152: 3 | Y152: TRUE | Z152: Play_voice_campaign_beginner00_43_02_bubble_Barbarianking | AA152: FALSE | AD152: 5.2593331 | AE152: 6.26 | AH152: 0.1 | AL152: 25 | AO152: 23 | AT152: =IF($AU152="","",SUBSTITUTE(SUBSTITUTE(SUBSTITUTE(SUBSTITUTE($AU152,IF($AW152="","",$AW152),IF($AW152="","",CONCATENATE("<color=#FFCC71>",$AW152,"</color>"))),IF($AX152="","",$AX152),IF($AX152="","",CONCATENATE("<color=#FFCC71>",$AX152,"</color>"))),IF($AY152="","",$AY152),IF($AY152="","",CONCATENATE("<color=#FFCC71>",$AY152,"</color>"))),IF($AZ152="","",$AZ152),IF($AZ152="","",CONCATENATE("<color=#FFCC71>",$AZ152,"</color>")))) -> 蛮族大军即将横扫整个帝国，你们无路可逃！ | AU152: 蛮族大军即将横扫整个帝国，你们无路可逃！
F153: =VLOOKUP(G153,'#TID_base_up'!B:C,2,0) -> #N/A | AA153: FALSE | AT153: =IF($AU153="","",SUBSTITUTE(SUBSTITUTE(SUBSTITUTE(SUBSTITUTE($AU153,IF($AW153="","",$AW153),IF($AW153="","",CONCATENATE("<color=#FFCC71>",$AW153,"</color>"))),IF($AX153="","",$AX153),IF($AX153="","",CONCATENATE("<color=#FFCC71>",$AX153,"</color>"))),IF($AY153="","",$AY153),IF($AY153="","",CONCATENATE("<color=#FFCC71>",$AY153,"</color>"))),IF($AZ153="","",$AZ153),IF($AZ153="","",CONCATENATE("<color=#FFCC71>",$AZ153,"</color>"))))
A154: 41101 | B154: 序章 | C154: 1 | D154: 新手序章 | E154: 海外S1 | F154: =VLOOKUP(G154,'#TID_base_up'!B:C,2,0) -> 凯撒 | G154: TID_DialogueConf_41101_name_CN_Main | H154: =VLOOKUP($G154,'#对话模型配置'!$A:$W,MATCH(对话配置表!H$2,'#对话模型配置'!$1:$1,0)) -> altasPath | I154: =VLOOKUP($G154,'#对话模型配置'!$A:$W,MATCH(对话配置表!I$2,'#对话模型配置'!$1:$1,0)) -> picture | J154: TID_DialogueConf_41101_textList_CN_Main | K154: =AT154 -> 大人，<color=#FFCC71>城门已被蛮族攻破</color>！我们要加快些，皇帝陛下的情况已经很危急了！ | U154: 1 | V154: 0 | X154: 3 | Y154: FALSE | Z154: Play_voice_story1_newbiebattle_04_gauis_en | AA154: FALSE | AC154: 20001007 | AD154: 6.4186668 | AE154: =AD154+1 -> 7.4186668 | AH154: 1.5 | AL154: 25 | AM154: =VLOOKUP($F154,'#对话模型配置'!$A:$W,MATCH(对话配置表!AM$2,'#对话模型配置'!$1:$1,0),FALSE) -> 0 | AN154: chapter_0_1 | AT154: =IF($AU154="","",SUBSTITUTE(SUBSTITUTE(SUBSTITUTE(SUBSTITUTE($AU154,IF($AW154="","",$AW154),IF($AW154="","",CONCATENATE("<color=#FFCC71>",$AW154,"</color>"))),IF($AX154="","",$AX154),IF($AX154="","",CONCATENATE("<color=#FFCC71>",$AX154,"</color>"))),IF($AY154="","",$AY154),IF($AY154="","",CONCATENATE("<color=#FFCC71>",$AY154,"</color>"))),IF($AZ154="","",$AZ154),IF($AZ154="","",CONCATENATE("<color=#FFCC71>",$AZ154,"</color>")))) -> 大人，<color=#FFCC71>城门已被蛮族攻破</color>！我们要加快些，皇帝陛下的情况已经很危急了！ | AU154: 大人，城门已被蛮族攻破！我们要加快些，皇帝陛下的情况已经很危急了！ | AW154: 城门已被蛮族攻破
A155: 41102 | B155: 序章 | C155: 1 | D155: 新手序章 | E155: 海外S1 | F155: =VLOOKUP(G155,'#TID_base_up'!B:C,2,0) -> 帝国斥候 | G155: TID_DialogueConf_41003_name_CN_Main | H155: =VLOOKUP($G155,'#对话模型配置'!$A:$W,MATCH(对话配置表!H$2,'#对话模型配置'!$1:$1,0)) -> altasPath | I155: =VLOOKUP($G155,'#对话模型配置'!$A:$W,MATCH(对话配置表!I$2,'#对话模型配置'!$1:$1,0)) -> picture | J155: TID_DialogueConf_41009_textList_CN_Main | K155: =AT155 -> 撑住！援军快要来了！ | U155: 4 | V155: 1 | X155: 3 | Y155: FALSE | Z155: Play_voice_story1_newbiebattle_05_iaf_en | AA155: FALSE | AD155: 2.7520001 | AE155: =AD155+1 -> 3.7520001 | AH155: 1.5 | AL155: 25 | AO155: 6 | AQ155: 0;-100 | AT155: =IF($AU155="","",SUBSTITUTE(SUBSTITUTE(SUBSTITUTE(SUBSTITUTE($AU155,IF($AW155="","",$AW155),IF($AW155="","",CONCATENATE("<color=#FFCC71>",$AW155,"</color>"))),IF($AX155="","",$AX155),IF($AX155="","",CONCATENATE("<color=#FFCC71>",$AX155,"</color>"))),IF($AY155="","",$AY155),IF($AY155="","",CONCATENATE("<color=#FFCC71>",$AY155,"</color>"))),IF($AZ155="","",$AZ155),IF($AZ155="","",CONCATENATE("<color=#FFCC71>",$AZ155,"</color>")))) -> 撑住！援军快要来了！ | AU155: 撑住！援军快要来了！
A156: 41103 | B156: 序章 | C156: 1 | D156: 新手序章 | E156: 海外S1 | F156: =VLOOKUP(G156,'#TID_base_up'!B:C,2,0) -> 凯撒 | G156: TID_DialogueConf_41101_name_CN_Main | H156: =VLOOKUP($G156,'#对话模型配置'!$A:$W,MATCH(对话配置表!H$2,'#对话模型配置'!$1:$1,0)) -> altasPath | I156: =VLOOKUP($G156,'#对话模型配置'!$A:$W,MATCH(对话配置表!I$2,'#对话模型配置'!$1:$1,0)) -> picture | J156: TID_DialogueConf_41103_textList_CN_Main | K156: =AT156 -> 剑士克制枪兵！利用我们的兵种优势，冲散他们！ | U156: 4 | V156: 0 | X156: 3 | Y156: TRUE | Z156: Play_voice_story1_newbiebattle_07_gauis_en | AA156: FALSE | AD156: 5.5786672 | AE156: =AD156+1 -> 6.5786672 | AH156: 0.1 | AL156: 25 | AO156: 1 | AT156: =IF($AU156="","",SUBSTITUTE(SUBSTITUTE(SUBSTITUTE(SUBSTITUTE($AU156,IF($AW156="","",$AW156),IF($AW156="","",CONCATENATE("<color=#FFCC71>",$AW156,"</color>"))),IF($AX156="","",$AX156),IF($AX156="","",CONCATENATE("<color=#FFCC71>",$AX156,"</color>"))),IF($AY156="","",$AY156),IF($AY156="","",CONCATENATE("<color=#FFCC71>",$AY156,"</color>"))),IF($AZ156="","",$AZ156),IF($AZ156="","",CONCATENATE("<color=#FFCC71>",$AZ156,"</color>")))) -> 剑士克制枪兵！利用我们的兵种优势，冲散他们！ | AU156: 剑士克制枪兵！利用我们的兵种优势，冲散他们！
A157: 41104 | B157: 序章 | C157: 1 | D157: 新手序章 | E157: 海外S1 | F157: =VLOOKUP(G157,'#TID_base_up'!B:C,2,0) -> 帝国斥候 | G157: TID_DialogueConf_41003_name_CN_Main | H157: =VLOOKUP($G157,'#对话模型配置'!$A:$W,MATCH(对话配置表!H$2,'#对话模型配置'!$1:$1,0)) -> altasPath | I157: =VLOOKUP($G157,'#对话模型配置'!$A:$W,MATCH(对话配置表!I$2,'#对话模型配置'!$1:$1,0)) -> picture | J157: TID_DialogueConf_41104_textList_CN_Main | K157: =AT157 -> 敌人处于残血状态！快使用[主将技能]收割他们！ | U157: 4 | V157: 2 | X157: 3 | Y157: TRUE | Z157: Play_voice_story1_newbiebattle_08_is_en | AA157: TRUE | AD157: 4.0799999 | AE157: =AD157+1 -> 5.0799999 | AH157: 0.1 | AL157: 25 | AO157: 1 | AQ157: 0;-60 | AT157: =IF($AU157="","",SUBSTITUTE(SUBSTITUTE(SUBSTITUTE(SUBSTITUTE($AU157,IF($AW157="","",$AW157),IF($AW157="","",CONCATENATE("<color=#FFCC71>",$AW157,"</color>"))),IF($AX157="","",$AX157),IF($AX157="","",CONCATENATE("<color=#FFCC71>",$AX157,"</color>"))),IF($AY157="","",$AY157),IF($AY157="","",CONCATENATE("<color=#FFCC71>",$AY157,"</color>"))),IF($AZ157="","",$AZ157),IF($AZ157="","",CONCATENATE("<color=#FFCC71>",$AZ157,"</color>")))) -> 敌人处于残血状态！快使用[主将技能]收割他们！ | AU157: 敌人处于残血状态！快使用[主将技能]收割他们！
A158: 41105 | B158: 序章 | C158: 1 | D158: 新手序章 | E158: 海外S1 | F158: =VLOOKUP(G158,'#TID_base_up'!B:C,2,0) -> 安德莉娅 | G158: TID_DialogueConf_2055001_name_CN_Main | H158: =VLOOKUP($G158,'#对话模型配置'!$A:$W,MATCH(对话配置表!H$2,'#对话模型配置'!$1:$1,0)) -> altasPath | I158: =VLOOKUP($G158,'#对话模型配置'!$A:$W,MATCH(对话配置表!I$2,'#对话模型配置'!$1:$1,0)) -> picture | J158: TID_DialogueConf_41105_textList_CN_Main | K158: =AT158 -> 还以为你们有多厉害呢，原来就这点能耐吗？ | U158: 4 | V158: 0 | X158: 3 | Y158: TRUE | Z158: Play_voice_story1_newbiebattle_10_andrea_en | AA158: FALSE | AD158: 4.2639999 | AE158: =AD158+1 -> 5.2639999 | AH158: 0.1 | AL158: 25 | AO158: 17 | AQ158: -40;-70 | AT158: =IF($AU158="","",SUBSTITUTE(SUBSTITUTE(SUBSTITUTE(SUBSTITUTE($AU158,IF($AW158="","",$AW158),IF($AW158="","",CONCATENATE("<color=#FFCC71>",$AW158,"</color>"))),IF($AX158="","",$AX158),IF($AX158="","",CONCATENATE("<color=#FFCC71>",$AX158,"</color>"))),IF($AY158="","",$AY158),IF($AY158="","",CONCATENATE("<color=#FFCC71>",$AY158,"</color>"))),IF($AZ158="","",$AZ158),IF($AZ158="","",CONCATENATE("<color=#FFCC71>",$AZ158,"</color>")))) -> 还以为你们有多厉害呢，原来就这点能耐吗？ | AU158: 还以为你们有多厉害呢，原来就这点能耐吗？
A159: 41106 | B159: 序章 | C159: 1 | D159: 新手序章 | E159: 海外S1 | F159: =VLOOKUP(G159,'#TID_base_up'!B:C,2,0) -> 蛮族前锋 | G159: TID_DialogueConf_41013_name_CN_Main | H159: =VLOOKUP($G159,'#对话模型配置'!$A:$W,MATCH(对话配置表!H$2,'#对话模型配置'!$1:$1,0)) -> altasPath | I159: =VLOOKUP($G159,'#对话模型配置'!$A:$W,MATCH(对话配置表!I$2,'#对话模型配置'!$1:$1,0)) -> picture | J159: TID_DialogueConf_41013_textList_CN_Main | K159: =AT159 -> 牙尖嘴利，一会儿看我怎么收拾你！ | U159: 4 | V159: 0 | X159: 3 | Y159: TRUE | Z159: Play_voice_story1_newbiebattle_11_bv_en | AA159: FALSE | AD159: 2.312 | AE159: =AD159+1 -> 3.312 | AH159: 0.1 | AL159: 25 | AO159: 17 | AQ159: -30;-75 | AT159: =IF($AU159="","",SUBSTITUTE(SUBSTITUTE(SUBSTITUTE(SUBSTITUTE($AU159,IF($AW159="","",$AW159),IF($AW159="","",CONCATENATE("<color=#FFCC71>",$AW159,"</color>"))),IF($AX159="","",$AX159),IF($AX159="","",CONCATENATE("<color=#FFCC71>",$AX159,"</color>"))),IF($AY159="","",$AY159),IF($AY159="","",CONCATENATE("<color=#FFCC71>",$AY159,"</color>"))),IF($AZ159="","",$AZ159),IF($AZ159="","",CONCATENATE("<color=#FFCC71>",$AZ159,"</color>")))) -> 牙尖嘴利，一会儿看我怎么收拾你！ | AU159: 牙尖嘴利，一会儿看我怎么收拾你！
A160: 41107 | B160: 序章 | C160: 1 | D160: 新手序章 | E160: 海外S1 | F160: =VLOOKUP(G160,'#TID_base_up'!B:C,2,0) -> 凯撒 | G160: TID_DialogueConf_41101_name_CN_Main | H160: =VLOOKUP($G160,'#对话模型配置'!$A:$W,MATCH(对话配置表!H$2,'#对话模型配置'!$1:$1,0)) -> altasPath | I160: =VLOOKUP($G160,'#对话模型配置'!$A:$W,MATCH(对话配置表!I$2,'#对话模型配置'!$1:$1,0)) -> picture | J160: TID_DialogueConf_41107_textList_CN_Main | K160: =AT160 -> 别怕，公主殿下！有我凯撒在，他们…… | U160: 4 | V160: 0 | X160: 3 | Y160: TRUE | Z160: Play_voice_story1_newbiebattle_14_gauis_en | AA160: FALSE | AD160: 5.1946669 | AE160: =AD160+1 -> 6.1946669 | AH160: 0.1 | AL160: 25 | AO160: 1 | AQ160: 0;-60 | AT160: =IF($AU160="","",SUBSTITUTE(SUBSTITUTE(SUBSTITUTE(SUBSTITUTE($AU160,IF($AW160="","",$AW160),IF($AW160="","",CONCATENATE("<color=#FFCC71>",$AW160,"</color>"))),IF($AX160="","",$AX160),IF($AX160="","",CONCATENATE("<color=#FFCC71>",$AX160,"</color>"))),IF($AY160="","",$AY160),IF($AY160="","",CONCATENATE("<color=#FFCC71>",$AY160,"</color>"))),IF($AZ160="","",$AZ160),IF($AZ160="","",CONCATENATE("<color=#FFCC71>",$AZ160,"</color>")))) -> 别怕，公主殿下！有我凯撒在，他们…… | AU160: 别怕，公主殿下！有我凯撒在，他们……
A161: 41108 | B161: 序章 | C161: 1 | D161: 新手序章 | E161: 海外S1 | F161: =VLOOKUP(G161,'#TID_base_up'!B:C,2,0) -> 安德莉娅 | G161: TID_DialogueConf_2055001_name_CN_Main | H161: =VLOOKUP($G161,'#对话模型配置'!$A:$W,MATCH(对话配置表!H$2,'#对话模型配置'!$1:$1,0)) -> altasPath | I161: =VLOOKUP($G161,'#对话模型配置'!$A:$W,MATCH(对话配置表!I$2,'#对话模型配置'!$1:$1,0)) -> picture | J161: TID_DialogueConf_41108_textList_CN_Main | K161: =AT161 -> 别废话了，快过来帮帮我！ | U161: 4 | V161: 0 | X161: 3 | Y161: TRUE | Z161: Play_voice_story1_newbiebattle_15_andrea_en | AA161: FALSE | AD161: 2.8053329 | AE161: =AD161+1 -> 3.8053329 | AH161: 0.1 | AL161: 25 | AO161: 17 | AQ161: -110;-100 | AT161: =IF($AU161="","",SUBSTITUTE(SUBSTITUTE(SUBSTITUTE(SUBSTITUTE($AU161,IF($AW161="","",$AW161),IF($AW161="","",CONCATENATE("<color=#FFCC71>",$AW161,"</color>"))),IF($AX161="","",$AX161),IF($AX161="","",CONCATENATE("<color=#FFCC71>",$AX161,"</color>"))),IF($AY161="","",$AY161),IF($AY161="","",CONCATENATE("<color=#FFCC71>",$AY161,"</color>"))),IF($AZ161="","",$AZ161),IF($AZ161="","",CONCATENATE("<color=#FFCC71>",$AZ161,"</color>")))) -> 别废话了，快过来帮帮我！ | AU161: 别废话了，快过来帮帮我！
A162: 41109 | B162: 序章 | C162: 1 | D162: 新手序章 | E162: 海外S1 | F162: =VLOOKUP(G162,'#TID_base_up'!B:C,2,0) -> 蛮王 | G162: TID_DialogueConf_41016_name_CN_Main | H162: =VLOOKUP($G162,'#对话模型配置'!$A:$W,MATCH(对话配置表!H$2,'#对话模型配置'!$1:$1,0)) -> altasPath | I162: =VLOOKUP($G162,'#对话模型配置'!$A:$W,MATCH(对话配置表!I$2,'#对话模型配置'!$1:$1,0)) -> picture | J162: TID_DialogueConf_41109_textList_CN_Main | K162: =AT162 -> 老家伙，别做无谓的挣扎了，快投降吧！ | U162: 4 | V162: 0 | X162: 3 | Y162: TRUE | Z162: Play_voice_story1_newbiebattle_16_bc_en | AA162: FALSE | AD162: 5.1680002 | AE162: =AD162+1 -> 6.1680002 | AH162: 0.1 | AL162: 25 | AO162: 23 | AQ162: 0;-60 | AT162: =IF($AU162="","",SUBSTITUTE(SUBSTITUTE(SUBSTITUTE(SUBSTITUTE($AU162,IF($AW162="","",$AW162),IF($AW162="","",CONCATENATE("<color=#FFCC71>",$AW162,"</color>"))),IF($AX162="","",$AX162),IF($AX162="","",CONCATENATE("<color=#FFCC71>",$AX162,"</color>"))),IF($AY162="","",$AY162),IF($AY162="","",CONCATENATE("<color=#FFCC71>",$AY162,"</color>"))),IF($AZ162="","",$AZ162),IF($AZ162="","",CONCATENATE("<color=#FFCC71>",$AZ162,"</color>")))) -> 老家伙，别做无谓的挣扎了，快投降吧！ | AU162: 老家伙，别做无谓的挣扎了，快投降吧！
A163: 41110 | B163: 序章 | C163: 1 | D163: 新手序章 | E163: 海外S1 | F163: =VLOOKUP(G163,'#TID_base_up'!B:C,2,0) -> 皇帝 | G163: TID_DialogueConf_41017_name_CN_Main | H163: =VLOOKUP($G163,'#对话模型配置'!$A:$W,MATCH(对话配置表!H$2,'#对话模型配置'!$1:$1,0)) -> altasPath | I163: =VLOOKUP($G163,'#对话模型配置'!$A:$W,MATCH(对话配置表!I$2,'#对话模型配置'!$1:$1,0)) -> picture | J163: TID_DialogueConf_41017_textList_CN_Main | K163: =AT163 -> 化外蛮夷，今天就让我来教教你，什么是基本礼仪！ | U163: 4 | V163: 0 | X163: 3 | Y163: TRUE | Z163: Play_voice_story1_newbiebattle_17_cstt_en | AA163: FALSE | AD163: 4.037333 | AE163: =AD163+1 -> 5.037333 | AH163: 0.1 | AL163: 25 | AO163: 32 | AQ163: -90;-60 | AT163: =IF($AU163="","",SUBSTITUTE(SUBSTITUTE(SUBSTITUTE(SUBSTITUTE($AU163,IF($AW163="","",$AW163),IF($AW163="","",CONCATENATE("<color=#FFCC71>",$AW163,"</color>"))),IF($AX163="","",$AX163),IF($AX163="","",CONCATENATE("<color=#FFCC71>",$AX163,"</color>"))),IF($AY163="","",$AY163),IF($AY163="","",CONCATENATE("<color=#FFCC71>",$AY163,"</color>"))),IF($AZ163="","",$AZ163),IF($AZ163="","",CONCATENATE("<color=#FFCC71>",$AZ163,"</color>")))) -> 化外蛮夷，今天就让我来教教你，什么是基本礼仪！ | AU163: 化外蛮夷，今天就让我来教教你，什么是基本礼仪！
A164: 41111 | B164: 序章 | C164: 1 | D164: 新手序章 | E164: 海外S1 | F164: =VLOOKUP(G164,'#TID_base_up'!B:C,2,0) -> 安德莉娅 | G164: TID_DialogueConf_2055001_name_CN_Main | H164: =VLOOKUP($G164,'#对话模型配置'!$A:$W,MATCH(对话配置表!H$2,'#对话模型配置'!$1:$1,0)) -> altasPath | I164: =VLOOKUP($G164,'#对话模型配置'!$A:$W,MATCH(对话配置表!I$2,'#对话模型配置'!$1:$1,0)) -> picture | J164: TID_DialogueConf_41033_textList_CN_Main | K164: =AT164 -> 领主大人，擒贼先擒王，快<color=#FFCC71>集合队伍</color>全力进攻敌人头目！ | U164: 1 | V164: 0 | X164: 3 | Y164: TRUE | Z164: Play_voice_story1_newbiebattle_18_andrea_en | AA164: FALSE | AC164: 20001008 | AD164: 7.6853328 | AE164: =AD164+1 -> 8.6853328 | AH164: 0.1 | AL164: 25 | AM164: =VLOOKUP($F164,'#对话模型配置'!$A:$W,MATCH(对话配置表!AM$2,'#对话模型配置'!$1:$1,0),FALSE) -> 30001001 | AN164: chapter_0_6 | AT164: =IF($AU164="","",SUBSTITUTE(SUBSTITUTE(SUBSTITUTE(SUBSTITUTE($AU164,IF($AW164="","",$AW164),IF($AW164="","",CONCATENATE("<color=#FFCC71>",$AW164,"</color>"))),IF($AX164="","",$AX164),IF($AX164="","",CONCATENATE("<color=#FFCC71>",$AX164,"</color>"))),IF($AY164="","",$AY164),IF($AY164="","",CONCATENATE("<color=#FFCC71>",$AY164,"</color>"))),IF($AZ164="","",$AZ164),IF($AZ164="","",CONCATENATE("<color=#FFCC71>",$AZ164,"</color>")))) -> 领主大人，擒贼先擒王，快<color=#FFCC71>集合队伍</color>全力进攻敌人头目！ | AU164: 领主大人，擒贼先擒王，快集合队伍全力进攻敌人头目！ | AW164: 集合队伍
A165: 41112 | B165: 序章 | C165: 1 | D165: 新手序章 | E165: 海外S1 | F165: =VLOOKUP(G165,'#TID_base_up'!B:C,2,0) -> 凯撒 | G165: TID_DialogueConf_41101_name_CN_Main | H165: =VLOOKUP($G165,'#对话模型配置'!$A:$W,MATCH(对话配置表!H$2,'#对话模型配置'!$1:$1,0)) -> altasPath | I165: =VLOOKUP($G165,'#对话模型配置'!$A:$W,MATCH(对话配置表!I$2,'#对话模型配置'!$1:$1,0)) -> picture | J165: TID_DialogueConf_41031_textList_CN_Main | K165: =AT165 -> 听我号令，全军出击，碾碎他们！ | U165: 4 | V165: 0 | X165: 3 | Y165: TRUE | Z165: Play_voice_story1_newbiebattle_21_gauis_en | AA165: FALSE | AD165: 2.922667 | AE165: =AD165+1 -> 3.922667 | AH165: 0.1 | AL165: 25 | AO165: 1 | AT165: =IF($AU165="","",SUBSTITUTE(SUBSTITUTE(SUBSTITUTE(SUBSTITUTE($AU165,IF($AW165="","",$AW165),IF($AW165="","",CONCATENATE("<color=#FFCC71>",$AW165,"</color>"))),IF($AX165="","",$AX165),IF($AX165="","",CONCATENATE("<color=#FFCC71>",$AX165,"</color>"))),IF($AY165="","",$AY165),IF($AY165="","",CONCATENATE("<color=#FFCC71>",$AY165,"</color>"))),IF($AZ165="","",$AZ165),IF($AZ165="","",CONCATENATE("<color=#FFCC71>",$AZ165,"</color>")))) -> 听我号令，全军出击，碾碎他们！ | AU165: 听我号令，全军出击，碾碎他们！
A166: 41113 | B166: 序章 | C166: 1 | D166: 新手序章 | E166: 海外S1 | F166: =VLOOKUP(G166,'#TID_base_up'!B:C,2,0) -> 皇帝 | G166: TID_DialogueConf_41017_name_CN_Main | H166: =VLOOKUP($G166,'#对话模型配置'!$A:$W,MATCH(对话配置表!H$2,'#对话模型配置'!$1:$1,0)) -> altasPath | I166: =VLOOKUP($G166,'#对话模型配置'!$A:$W,MATCH(对话配置表!I$2,'#对话模型配置'!$1:$1,0)) -> picture | J166: TID_DialogueConf_41019_textList_CN_Main | K166: =AT166 -> 想不到，最后竟然只有你来陪我打这一场仗！ | U166: 4 | V166: 0 | X166: 3 | Y166: TRUE | Z166: Play_voice_story1_newbiebattle_22_cstt_en | AA166: FALSE | AD166: 4.5493331 | AE166: =AD166+1 -> 5.5493331 | AH166: 0.1 | AL166: 25 | AO166: 32 | AQ166: -90;-95 | AT166: =IF($AU166="","",SUBSTITUTE(SUBSTITUTE(SUBSTITUTE(SUBSTITUTE($AU166,IF($AW166="","",$AW166),IF($AW166="","",CONCATENATE("<color=#FFCC71>",$AW166,"</color>"))),IF($AX166="","",$AX166),IF($AX166="","",CONCATENATE("<color=#FFCC71>",$AX166,"</color>"))),IF($AY166="","",$AY166),IF($AY166="","",CONCATENATE("<color=#FFCC71>",$AY166,"</color>"))),IF($AZ166="","",$AZ166),IF($AZ166="","",CONCATENATE("<color=#FFCC71>",$AZ166,"</color>")))) -> 想不到，最后竟然只有你来陪我打这一场仗！ | AU166: 想不到，最后竟然只有你来陪我打这一场仗！
A167: 41114 | B167: 序章 | C167: 1 | D167: 新手序章 | E167: 海外S1 | F167: =VLOOKUP(G167,'#TID_base_up'!B:C,2,0) -> 蛮王 | G167: TID_DialogueConf_41016_name_CN_Main | H167: =VLOOKUP($G167,'#对话模型配置'!$A:$W,MATCH(对话配置表!H$2,'#对话模型配置'!$1:$1,0)) -> altasPath | I167: =VLOOKUP($G167,'#对话模型配置'!$A:$W,MATCH(对话配置表!I$2,'#对话模型配置'!$1:$1,0)) -> picture | J167: TID_DialogueConf_41114_textList_CN_Main | K167: =AT167 -> 可笑，见过逃跑的，还没见过赶着送死的！ | U167: 4 | V167: 0 | X167: 3 | Y167: TRUE | Z167: Play_voice_story1_newbiebattle_23_bc_en | AA167: FALSE | AD167: 5.1973329 | AE167: =AD167+1 -> 6.1973329 | AH167: 0.1 | AL167: 25 | AO167: 23 | AQ167: -90;-15 | AT167: =IF($AU167="","",SUBSTITUTE(SUBSTITUTE(SUBSTITUTE(SUBSTITUTE($AU167,IF($AW167="","",$AW167),IF($AW167="","",CONCATENATE("<color=#FFCC71>",$AW167,"</color>"))),IF($AX167="","",$AX167),IF($AX167="","",CONCATENATE("<color=#FFCC71>",$AX167,"</color>"))),IF($AY167="","",$AY167),IF($AY167="","",CONCATENATE("<color=#FFCC71>",$AY167,"</color>"))),IF($AZ167="","",$AZ167),IF($AZ167="","",CONCATENATE("<color=#FFCC71>",$AZ167,"</color>")))) -> 可笑，见过逃跑的，还没见过赶着送死的！ | AU167: 可笑，见过逃跑的，还没见过赶着送死的！
A168: 41115 | B168: 序章 | C168: 1 | D168: 新手序章 | E168: 海外S1 | F168: =VLOOKUP(G168,'#TID_base_up'!B:C,2,0) -> 安德莉娅 | G168: TID_DialogueConf_2055001_name_CN_Main | H168: =VLOOKUP($G168,'#对话模型配置'!$A:$W,MATCH(对话配置表!H$2,'#对话模型配置'!$1:$1,0)) -> altasPath | I168: =VLOOKUP($G168,'#对话模型配置'!$A:$W,MATCH(对话配置表!I$2,'#对话模型配置'!$1:$1,0)) -> picture | J168: TID_DialogueConf_41026_textList_CN_Main | K168: =AT168 -> 蛮王又准备施放技能了，快打断他！ | U168: 4 | V168: 0 | X168: 3 | Y168: TRUE | Z168: Play_voice_story1_newbiebattle_25_andrea_en | AA168: TRUE | AD168: 4.2026672 | AE168: =AD168+1 -> 5.2026672 | AH168: 0.1 | AL168: 25 | AO168: 17 | AT168: =IF($AU168="","",SUBSTITUTE(SUBSTITUTE(SUBSTITUTE(SUBSTITUTE($AU168,IF($AW168="","",$AW168),IF($AW168="","",CONCATENATE("<color=#FFCC71>",$AW168,"</color>"))),IF($AX168="","",$AX168),IF($AX168="","",CONCATENATE("<color=#FFCC71>",$AX168,"</color>"))),IF($AY168="","",$AY168),IF($AY168="","",CONCATENATE("<color=#FFCC71>",$AY168,"</color>"))),IF($AZ168="","",$AZ168),IF($AZ168="","",CONCATENATE("<color=#FFCC71>",$AZ168,"</color>")))) -> 蛮王又准备施放技能了，快打断他！ | AU168: 蛮王又准备施放技能了，快打断他！
A169: 41116 | B169: 序章 | C169: 1 | D169: 新手序章 | E169: 海外S1 | F169: =VLOOKUP(G169,'#TID_base_up'!B:C,2,0) -> 凯撒 | G169: TID_DialogueConf_41101_name_CN_Main | H169: =VLOOKUP($G169,'#对话模型配置'!$A:$W,MATCH(对话配置表!H$2,'#对话模型配置'!$1:$1,0)) -> altasPath | I169: =VLOOKUP($G169,'#对话模型配置'!$A:$W,MATCH(对话配置表!I$2,'#对话模型配置'!$1:$1,0)) -> picture | J169: TID_DialogueConf_41116_textList_CN_Main | K169: =AT169 -> 让我来，再多枪兵也都是我剑下炮灰！ | U169: 4 | V169: 0 | X169: 3 | Y169: TRUE | Z169: Play_voice_story1_newbiebattle_26_gauis_en | AA169: FALSE | AD169: 4.2253332 | AE169: =AD169+1 -> 5.2253332 | AH169: 0.1 | AL169: 25 | AO169: 1 | AT169: =IF($AU169="","",SUBSTITUTE(SUBSTITUTE(SUBSTITUTE(SUBSTITUTE($AU169,IF($AW169="","",$AW169),IF($AW169="","",CONCATENATE("<color=#FFCC71>",$AW169,"</color>"))),IF($AX169="","",$AX169),IF($AX169="","",CONCATENATE("<color=#FFCC71>",$AX169,"</color>"))),IF($AY169="","",$AY169),IF($AY169="","",CONCATENATE("<color=#FFCC71>",$AY169,"</color>"))),IF($AZ169="","",$AZ169),IF($AZ169="","",CONCATENATE("<color=#FFCC71>",$AZ169,"</color>")))) -> 让我来，再多枪兵也都是我剑下炮灰！ | AU169: 让我来，再多枪兵也都是我剑下炮灰！
A170: 41117 | B170: 序章 | C170: 1 | D170: 新手序章 | E170: 海外S1 | F170: =VLOOKUP(G170,'#TID_base_up'!B:C,2,0) -> 蛮王 | G170: TID_DialogueConf_41016_name_CN_Main | H170: =VLOOKUP($G170,'#对话模型配置'!$A:$W,MATCH(对话配置表!H$2,'#对话模型配置'!$1:$1,0)) -> altasPath | I170: =VLOOKUP($G170,'#对话模型配置'!$A:$W,MATCH(对话配置表!I$2,'#对话模型配置'!$1:$1,0)) -> picture | J170: TID_DialogueConf_41117_textList_CN_Main | K170: =AT170 -> 哼，这老家伙就算让你带走又如何！ | U170: 4 | V170: 0 | X170: 3 | Y170: TRUE | Z170: Play_voice_story1_newbiebattle_27_bc_en | AA170: FALSE | AD170: 3.761333 | AE170: =AD170+1 -> 4.761333 | AH170: 0.1 | AL170: 25 | AO170: 23 | AT170: =IF($AU170="","",SUBSTITUTE(SUBSTITUTE(SUBSTITUTE(SUBSTITUTE($AU170,IF($AW170="","",$AW170),IF($AW170="","",CONCATENATE("<color=#FFCC71>",$AW170,"</color>"))),IF($AX170="","",$AX170),IF($AX170="","",CONCATENATE("<color=#FFCC71>",$AX170,"</color>"))),IF($AY170="","",$AY170),IF($AY170="","",CONCATENATE("<color=#FFCC71>",$AY170,"</color>"))),IF($AZ170="","",$AZ170),IF($AZ170="","",CONCATENATE("<color=#FFCC71>",$AZ170,"</color>")))) -> 哼，这老家伙就算让你带走又如何！ | AU170: 哼，这老家伙就算让你带走又如何！
...

Sheet Spine配置表
A1: convert(ResTask.proto, table_SpineConf, SpineConf.pbin)
A2: SpineId | B2: 说明 | C2: 序列 | D2: Spine路径 | E2: 文本 | F2: 语音和背景音
A3: spineId | C3: contextSequence | D3: spineName | E3: textList | F3: voiceList[|]
A4: 1 | C4: 1 | E4: TID_SpineConf_11_textList_CN_Main
A5: 1 | C5: 2 | E5: TID_SpineConf_12_textList_CN_Main
A6: 1 | C6: 3 | E6: TID_SpineConf_13_textList_CN_Main
A7: 2 | C7: 1 | E7: TID_SpineConf_21_textList_CN_Main
A8: 2 | C8: 2 | E8: TID_SpineConf_22_textList_CN_Main

Sheet #Sheet2
A1: npcid | B1: 模型路径 | C1: 动作名称
A2: id | B2: modePath | C2: animations[|]
A3: 1 | B3: assets/bundleresources/characters/story/p_celine_n_story.prefab | C3: Idle | D3: Walk | E3: Talk | F3: Down_Cry
A4: 2 | B4: assets/bundleresources/characters/story/p_fa_lan_ke_shibing1_story_anim.prefab | C4: Idle_Story | D4: run_Story | E4: attack_Story | F4: moan_Story
A5: 3 | B5: assets/bundleresources/characters/story/p_lead.prefab | C5: Idle | D5: Walk | E5: Attack | F5: wave
A6: 4 | B6: assets/bundleresources/characters/story/p_ma_ke_bo_luo_story_anim.prefab | C6: idle | D6: idleSpecial | E6: interaction | F6: walk
A7: 5 | B7: assets/bundleresources/characters/tv_preview/p_vikin_tv.prefab | C7: idle
A8: 6 | B8: assets/bundleresources/characters/tv_preview/p_bfnpc_hawker_tv.prefab | C8: idle
A9: 7 | B9: assets/bundleresources/characters/tv_preview/p_celine_n_tv.prefab | C9: idle | D9: talk | E9: think | F9: shout
A10: 8 | B10: assets/bundleresources/characters/tv_preview/p_lead_tv.prefab | C10: idle | D10: talk | E10: weak
A11: 9 | B11: assets/bundleresources/characters/tv_preview/p_fa_lan_ke_shibing1_tv.prefab | C11: idle_story | D11: standby_story
A12: 10 | B12: assets/bundleresources/characters/lobby/p_hero_boudica.prefab
A13: 11 | B13: assets/bundleresources/characters/lobby/p_hero_boudica_tv.prefab
A14: 12 | B14: assets/bundleresources/characters/tv_preview/p_a_flora_tv.prefab | C14: talk_normal | D14: talk_happy | E14: talk_angry | H14: 芙罗拉
A15: 13 | B15: assets/bundleresources/characters/tv_preview/p_a_lead_tv.prefab | C15: talk_normal | D15: talk_happy | E15: talk_angry | H15: 法兰克默认君主形象
A16: 14 | B16: assets/bundleresources/characters/tv_preview/p_a_lead_e01_tv.prefab | C16: talk_normal | D16: talk_happy | E16: talk_angry | H16: 中国默认君主形象
A17: 15 | B17: assets/bundleresources/characters/tv_preview/p_afl1_pkemn_tv.prefab | C17: idle | H17: 法兰克1级枪兵
A18: 16 | B18: assets/bundleresources/characters/tv_preview/p_afl2_pkemn_tv.prefab | C18: idle | H18: 法兰克2级枪兵
A19: 17 | B19: assets/bundleresources/characters/tv_preview/p_afl3_pkemn_tv.prefab | C19: DJ | H19: 法兰克3级枪兵
A20: 18 | B20: assets/bundleresources/characters/tv_preview/p_afl4_pkemn_tv.prefab | C20: DJ | H20: 法兰克4级枪兵
A21: 19 | B21: assets/bundleresources/characters/tv_preview/p_hero_boudica_tv.prefab | C21: idle | H21: 布狄卡
A22: 20 | B22: assets/bundleresources/characters/tv_preview/p_acl1_archr_tv.prefab | C22: tv_idle | H22: 中国1级弓兵-农民
A23: 21 | B23: assets/bundleresources/characters/tv_preview/p_acl1_archr_tv.prefab | C23: tv_idle | H23: 中国1级弓兵-农民
A24: 22 | B24: assets/bundleresources/characters/peasant/p_bfnpc_hawker_tv.prefab | C24: idle | H24: 小贩
A25: 23 | B25: assets/bundleresources/characters/tv_preview/p_bml4_huns_tv.prefab | C25: DJ | H25: 野蛮人头目
A26: 24 | B26: assets/bundleresources/characters/tv_preview/p_acl1_pkemn_tv.prefab | C26: tv_idle | H26: 中国1级枪兵-水手
A27: 25 | B27: assets/bundleresources/characters/tv_preview/p_acl3_pkemn_tv.prefab | C27: DJ | H27: 中国3级枪兵-随从
A28: 26 | B28: assets/bundleresources/characters/tv_preview/p_hero_hml_tv.prefab | C28: talk_normal | D28: talk_happy | E28: talk_angry | H28: 花木兰
A29: 27 | B29: assets/bundleresources/characters/tv_preview/p_hero_daxueshi_tv.prefab | C29: talk_normal | H29: 中国学士
A30: 28 | B30: assets/bundleresources/characters/tv_preview/p_a_leadm_e02.prefab | C30: talk_normal | D30: talk_happy | E30: talk_angry | H30: 中国默认君主形象
A31: 29 | B31: assets/bundleresources/characters/tv_preview/p_actv_bachelor_e.prefab | C31: talk_normal | H31: 中国学士
A32: 30 | B32: assets/bundleresources/characters/tv_preview/p_actv_retinue_e.prefab | C32: tv_idle | H32: 中国随从
A33: 31 | B33: assets/bundleresources/characters/tv_preview/p_actv_farmer_e.prefab | C33: tv_idle | H33: 中国村民

Sheet #Sheet1
J2: 琼恩 | K2: ="frame_s_xsdh_00"&L2 -> frame_s_xsdh_001 | L2: 1
J3: 强盗 | K3: ="frame_s_xsdh_00"&L3 -> frame_s_xsdh_005 | L3: 5
J4: 德·梅斯 | K4: ="frame_s_xsdh_00"&L4 -> frame_s_xsdh_003 | L4: 3
J5: 伯特兰 | K5: ="frame_s_xsdh_00"&L5 -> frame_s_xsdh_006 | L5: 6
J6: 强盗伏兵 | K6: ="frame_s_xsdh_00"&L6 -> frame_s_xsdh_005 | L6: 5
J7: 勃艮第人 | K7: ="frame_s_xsdh_00"&L7 -> frame_s_xsdh_005 | L7: 5
J8: 齐侬巡逻队 | K8: ="frame_s_xsdh_00"&L8 -> frame_s_xsdh_002 | L8: 2
J9: 齐侬巡查队 | K9: ="frame_s_xsdh_00"&L9 -> frame_s_xsdh_002 | L9: 2
J10: 萨佛克伯爵 | K10: ="frame_s_xsdh_00"&L10 -> frame_s_xsdh_005 | L10: 5

Sheet #名称Key
A1: 随从 | B1: SuiCong
A2: 我 | B2: Wo
A3: 村民甲 | B3: CunMinJia
A4: 魏兰 | B4: WeiLan
A5: 琼恩 | B5: QiongEn
A6: 强盗 | B6: QiangDao
A7: 德·梅斯 | B7: DeMeiSi
A8: 伯特兰 | B8: BoTeLan
A9: 强盗伏兵 | B9: QiangDaoFuBing1
A10: 勃艮第人 | B10: BoGenDiRen
A11: 齐侬巡逻队 | B11: QiNongXunLuoDui
A12: 齐侬巡查队 | B12: QiNongXunChaDui
... A45: 兵仙 | B45: BingXian

Sheet #对话模型配置
A1: 角色名称 | B1: 策划用模型 | C1: 文本 | D1: 是否使用3D播放 | E1: 语音和背景音 | F1: 语音和背景结束音 | G1: 口型配置 | H1: 自动关闭时间 | I1: 角色模型 | J1: 表演动作 | K1: 蓝图objID | L1: 角色名字key | M1: 图集路径 | N1: 海外新手用图集 | O1: 海外新手用头像 | P1: 图片 | Q1: 对话文本 | R1: 标签后文本 | S1: 初始文本 | T1: 标签文本1 | U1: 标签文本2 | V1: 标签文本3 | W1: 标签文本4
A2: name | C2: textList | D2: isIn3D | E2: voiceList[|] | F2: endVoiceList[|] | H2: endTime | I2: npcId | J2: animationName | K2: BPobjID | L2: hideBlur | M2: altasPath | N2: altasPath | O2: picture | P2: picture
A3: 帝国斥候 | H3: 10 | I3: 20001001 | J3: chapter_1_6 | M3: icon_guidechara.smash | P3: frame_s_xsdh_002
A4: 安德莉娅 | H4: 10 | I4: 30001001 | J4: chapter_1_2 | M4: icon_guidechara.smash | N4: icon_newbie | O4: newbie_oversea_andrea | P4: frame_s_xsdh_002
A5: 尤里乌斯 | H5: 10 | I5: 20001003 | J5: Idle | M5: icon_guidechara.smash | P5: frame_s_xsdh_002
A6: 关羽 | H6: 10 | I6: 20001004 | J6: Idle | M6: icon_guidechara.smash | P6: frame_s_xsdh_002
A7: 魏兰 | H7: 10 | I7: 20001005 | J7: chapter_1_2 | M7: icon_guidechara.smash | P7: frame_s_xsdh_002
A8: 皇帝 | H8: 10 | I8: 20001006 | J8: chapter_2_13 | M8: icon_guidechara.smash | P8: frame_s_xsdh_002
A9: 花木兰 | H9: 10 | I9: 20001005 | J9: chapter_1_2 | M9: icon_guidechara.smash | P9: frame_s_xsdh_002
A10: 尤里乌斯 | H10: 10 | I10: 20001003 | J10: Idle | M10: icon_guidechara.smash | P10: frame_s_xsdh_002
A11: 李白 | I11: 20001099
A12: 贞德 | B12: 110002 | H12: 10 | I12: 30001002 | J12: chapter_1_2 | L12: TID_DialogueConf_1060715_name_CN_Main | M12: icon_guidechara.smash | N12: icon_newbie | O12: newbie_oversea_joa | P12: frame_s_xsdh_002
A13: 副官 | B13: 110008 | H13: 10 | I13: 30001003 | J13: Idle | L13: TID_DialogueConf_1060001_name_CN_Main | M13: icon_guidechara.smash | N13: icon_newbie | O13: newbie_oversea_axe | P13: frame_s_xsdh_002
A14: 村民 | L14: TID_DialogueConf_1060611_name_CN_Main | N14: icon_newbie | O14: newbie_oversea_farmernohat
A15: 乌尔丁 | L15: TID_DialogueConf_1060607_name_CN_Main | N15: icon_newbie | O15: newbie_oversea_enemy
A16: 血手阿提卡 | L16: TID_DialogueConf_1060620_name_CN_Main | N16: icon_newbie | O16: newbie_oversea_attila
A17: 安德莉亚 | B17: 110003 | L17: TID_DialogueConf_1060001_name_337966742914_CN_Main | N17: icon_newbie | O17: newbie_oversea_andrea
A18: 凯恩 | N18: icon_newbie | O18: newbie_oversea_leo
A19: 肖恩 | N19: icon_newbie | O19: newbie_oversea_leo
A20: 蒙杜克 | L20: TID_Name_mengduke_CN_Main | N20: icon_newbie | O20: newbie_oversea_monduk
A21: 士兵 | L21: TID_Name_shibing_CN_Main | N21: icon_newbie | O21: newbie_oversea_leo
A22: 蛮族 | L22: TID_Dialogue_Character_6 | N22: icon_newbie | O22: newbie_oversea_enemy
A23: 温德 | L23: TID_Name_wende_CN_Main | N23: icon_newbie | O23: newbie_oversea_leo
A24: 图尔坎 | L24: TID_Name_tuerkan_CN_Main | N24: icon_newbie | O24: newbie_oversea_enemy
A25: 保罗 | L25: TID_Name_baoluo_CN_Main | N25: icon_newbie | O25: newbie_oversea_enemy
A26: 蛮族士兵 | L26: TID_Name_manzushibing_CN_Main | N26: icon_newbie | O26: newbie_oversea_enemy
A27: 研究员 | L27: TID_Name_yanjiuyuan_CN_Main | N27: icon_newbie | O27: newbie_oversea_enemy
A28: 珍妮 | L28: TID_Name_zhenni_CN_Main | N28: icon_newbie | O28: newbie_oversea_leo
A29: 陌生的来客 | B29: 110001 | L29: TID_Dialogue_Character_4 | N29: icon_newbie | O29: newbie_oversea_caesar
A30: 凯撒 | B30: 110001 | L30: TID_Dialogue_Character_5 | N30: icon_newbie | O30: newbie_oversea_caesar
A31: 部落 | B31: 110005 | L31: TID_Dialogue_Character_6 | N31: icon_newbie | O31: newbie_oversea_enemy
A32: 克洛维 | B32: 110004 | L32: TID_Dialogue_Character_7 | N32: icon_newbie | O32: newbie_oversea_clovis
A33: 撕裂者 | B33: 110005 | L33: TID_Dialogue_Character_8 | N33: icon_newbie | O33: newbie_oversea_kabar
A34: 墨西 | B34: 110006 | L34: TID_Dialogue_Character_9 | N34: icon_newbie | O34: newbie_oversea_mose
A35: 克鲁维斯 | B35: 110007 | L35: TID_Dialogue_Character_10 | N35: icon_hero | O35: story_kruvis_big
A36: 约瑟芬 | B36: 110003 | L36: TID_Dialogue_Character_11 | N36: icon_newbie | O36: newbie_oversea_andrea
A37: 卡尔 | L37: TID_Dialogue_Character_12 | N37: icon_newbie | O37: newbie_oversea_carl
A38: 近卫 | L38: xinshou_story_charname01 | N38: icon_newbie | O38: newbie_oversea_leo
A39: 副官big | L39: TID_DialogueConf_1060001_name_CN_Main | N39: icon_hero | O39: icon_hero_206_big
A40: 村民big | L40: TID_DialogueConf_1060611_name_CN_Main | N40: icon_hero | O40: newbie_farmer_big
A41: 乌尔丁big | L41: TID_DialogueConf_1060607_name_CN_Main | N41: icon_hero | O41: newbie_urdin_big
A42: 血手阿提卡big | L42: TID_DialogueConf_1060620_name_CN_Main | N42: icon_hero | O42: icon_hero_032_big
A43: 约瑟芬big | L43: TID_Dialogue_Character_11 | N43: icon_hero | O43: icon_hero_036_big
A44: 士兵big | L44: TID_Name_shibing_CN_Main | N44: icon_hero | O44: icon_hero_203_big
A45: 卡尔big | L45: TID_Dialogue_Character_12 | N45: icon_hero | O45: newbie_carl_big
A46: 阿克塞尔副官 | B46: 110008 | L46: TID_DialogueConf_1060001_name_CN_Main | N46: icon_hero | O46: icon_hero_206_big
A47: 奥斯汀 | B47: 110009 | L47: TID_Dialogue_story_gl_charaname_01 | N47: icon_hero | O47: story_austin_big
A48: 血鞭商人威尔 | B48: 110011 | L48: TID_Dialogue_story_gl_charaname_02 | N48: icon_hero | O48: story_will_big
A49: 琳达 | B49: 110012 | L49: TID_Dialogue_story_gl_charaname_03 | N49: icon_hero | O49: story_linda_big
A50: 杜尔村村民 | B50: 110010 | L50: TID_Dialogue_story_gl_charaname_04 | N50: icon_hero | O50: story_peasant_big
A51: 女修士 | B51: 110012 | L51: TID_Dialogue_story_gl_charaname_05 | N51: icon_hero | O51: story_linda_big
A52: 尼诺 | B52: 110006 | L52: TID_BaseHeroRecruitPool_10_ItemNameText_CN_Main | N52: icon_hero | O52: story_nino_big
A53: 圣物 | L53: TID_HolyDawn_Relic | N53: ui_g_holywar | O53: pic_holywar_icon_38

Sheet #TID_base_up
A1: 旧Key | B1: 新Key | C1: 文本
A2: DialogueConf_1001_name_CN_Main | B2: TID_DialogueConf_1001_name_CN_Main | C2: 随从
A3: DialogueConf_1_textList_CN_Main | B3: TID_DialogueConf_1_textList_CN_Main | C3: <color=#FFED6D>领主</color>，关押<color=#FFED6D>村民们</color>的营地就在前方。
A4: DialogueConf_2_name_23996658795_CN_Main | B4: TID_DialogueConf_2_name_23996658795_CN_Main | C4: 我
A5: DialogueConf_2_textList_CN_Main | B5: TID_DialogueConf_2_textList_CN_Main | C5: 必须<color=#FFED6D>拯救他们</color>。这是我跟<color=#FFED6D>姐姐</color>的约定？
A6: DialogueConf_2_textList_705307478613_CN_Main | B6: TID_DialogueConf_2_textList_705307478613_CN_Main | C6: 出发！消灭守军。
A7: DialogueConf_3_name_CN_Main | B7: TID_DialogueConf_3_name_CN_Main | C7: 村民甲
A8: DialogueConf_3_textList_CN_Main | B8: TID_DialogueConf_3_textList_CN_Main | C8: 天啊！敌人的将军来了，就在前方。
A9: DialogueConf_4_name_CN_Main | B9: TID_DialogueConf_4_name_CN_Main | C9: 魏兰
A10: DialogueConf_4_textList_CN_Main | B10: TID_DialogueConf_4_textList_CN_Main | C10: 我是<color=#FFED6D>魏兰</color>。前来营救！
A11: DialogueConf_5_textList_CN_Main | B11: TID_DialogueConf_5_textList_CN_Main | C11: 这是小对话测试1
A12: DialogueConf_5_textList_960981524853_CN_Main | B12: TID_DialogueConf_5_textList_960981524853_CN_Main | C12: 这是小对话测试2
... A847: SpineConf_22_textList_CN_Main | B847: TID_SpineConf_22_textList_CN_Main | C847: 新手剧情Spine5（占位） 皇帝阵亡之前，嘱托玩家一定要: “铲除蛮族，夺回皇城，统一帝国！”
